Workbook

Sheet Raw_data
A1: Order ID | B1: Order Date | C1: Customer ID | D1: Type | E1: SKU | F1: Category | G1: Product Name | H1: Unit Price | I1: Qty | J1: Total | K1: Discount Code | L1: Disc % | M1: Payment | N1: Source | O1: City | P1: State | Q1: Warehouse | R1: Del Date | S1: Status | T1: Return? | U1: Reason | V1: Ret Rec | W1: Refund | X1: valid_quantity_flag | Y1: Discount_amount | Z1: Net revenue | AA1: Average order value | AB1: Order_month | AC1: Order_week | AD1: Payment Type
A2: UT-100001 | B2: 45566 | C2: CUST_10001 | D2: New | E2: TOP-CAS-M | F2: Tops | G2: Classic Cotton Tee | H2: 1299 | I2: 2 | J2: 2598 | L2: 0 | M2: UPI | N2: Website | O2: Mumbai | P2: Maharashtra | Q2: Mumbai | R2: 45570 | S2: Delivered | T2: No | W2: Not Applicable | X2: =IF(urbanthreads_q4[[#This Row],[Qty]]>0,"Valid","Invalid") -> Valid | Y2: =urbanthreads_q4[[#This Row],[Total]]*urbanthreads_q4[[#This Row],[Disc %]]/100 -> 0 | Z2: =urbanthreads_q4[[#This Row],[Total]]-urbanthreads_q4[[#This Row],[Disc %]] -> 2598 | AA2: =urbanthreads_q4[[#This Row],[Net revenue]]/urbanthreads_q4[[#This Row],[Total]] -> 1 | AB2: =TEXT(urbanthreads_q4[[#This Row],[Order Date]],"mm-yyyy") -> 10-2024 | AC2: =YEAR(urbanthreads_q4[[#This Row],[Order Date]]) & "-W" & WEEKNUM(urbanthreads_q4[[#This Row],[Order Date]], 2) -> 2024-W40 | AD2: =IF(urbanthreads_q4[[#This Row],[Payment]]="COD","COD","Prepaid") -> Prepaid
A3: UT-100343 | B3: 45656 | C3: CUST_10342 | D3: New | E3: OUT-FRE-M | F3: Outerwear | G3: Fresh Start Jacket | H3: 4899 | I3: 1 | J3: 4899 | K3: Dec20 | L3: 20 | M3: COD | N3: Website | O3: Mumbai | P3: Maharashtra | Q3: Mumbai | R3: 45684 | S3: Delivered | T3: Yes | U3: Wrong Item | V3: 45712 | W3: Processed | X3: =IF(urbanthreads_q4[[#This Row],[Qty]]>0,"Valid","Invalid") -> Valid | Y3: =urbanthreads_q4[[#This Row],[Total]]*urbanthreads_q4[[#This Row],[Disc %]]/100 -> 979.8 | Z3: =urbanthreads_q4[[#This Row],[Total]]-urbanthreads_q4[[#This Row],[Disc %]] -> 4879 | AA3: =urbanthreads_q4[[#This Row],[Net revenue]]/urbanthreads_q4[[#This Row],[Total]] -> 0.99591753 | AB3: =TEXT(urbanthreads_q4[[#This Row],[Order Date]],"mm-yyyy") -> 12-2024 | AC3: =YEAR(urbanthreads_q4[[#This Row],[Order Date]]) & "-W" & WEEKNUM(urbanthreads_q4[[#This Row],[Order Date]], 2) -> 2024-W53 | AD3: =IF(urbanthreads_q4[[#This Row],[Payment]]="COD","COD","Prepaid") -> COD
A4: UT-100003 | B4: 45301 | C4: CUST_10003 | D4: new | E4: BOT-JNS-L | F4: Bottoms | G4: Slim Fit Jeans | H4: 1899 | I4: 1 | J4: 1899 | L4: 0 | M4: COD | N4: Website | O4: Bangalore | P4: Karnataka | Q4: Bangalore | R4: 45571 | S4: Delivered | T4: No | W4: Not Applicable | X4: =IF(urbanthreads_q4[[#This Row],[Qty]]>0,"Valid","Invalid") -> Valid | Y4: =urbanthreads_q4[[#This Row],[Total]]*urbanthreads_q4[[#This Row],[Disc %]]/100 -> 0 | Z4: =urbanthreads_q4[[#This Row],[Total]]-urbanthreads_q4[[#This Row],[Disc %]] -> 1899 | AA4: =urbanthreads_q4[[#This Row],[Net revenue]]/urbanthreads_q4[[#This Row],[Total]] -> 1 | AB4: =TEXT(urbanthreads_q4[[#This Row],[Order Date]],"mm-yyyy") -> 01-2024 | AC4: =YEAR(urbanthreads_q4[[#This Row],[Order Date]]) & "-W" & WEEKNUM(urbanthreads_q4[[#This Row],[Order Date]], 2) -> 2024-W2 | AD4: =IF(urbanthreads_q4[[#This Row],[Payment]]="COD","COD","Prepaid") -> COD
A5: UT-100345 | B5: 45656 | C5: CUST_10344 | D5: New | E5: TOP-BEG-L | F5: Tops | G5: Begin Again Top | H5: 2199 | I5: 1 | J5: 2199 | L5: 0 | M5: Debit Card | N5: Instagram Shop | O5: Chandigarh | P5: Punjab | Q5: Delhi | R5: 45684 | S5: Delivered | T5: Yes | U5: Damaged in Transit | V5: 45711 | W5: Processed | X5: =IF(urbanthreads_q4[[#This Row],[Qty]]>0,"Valid","Invalid") -> Valid | Y5: =urbanthreads_q4[[#This Row],[Total]]*urbanthreads_q4[[#This Row],[Disc %]]/100 -> 0 | Z5: =urbanthreads_q4[[#This Row],[Total]]-urbanthreads_q4[[#This Row],[Disc %]] -> 2199 | AA5: =urbanthreads_q4[[#This Row],[Net revenue]]/urbanthreads_q4[[#This Row],[Total]] -> 1 | AB5: =TEXT(urbanthreads_q4[[#This Row],[Order Date]],"mm-yyyy") -> 12-2024 | AC5: =YEAR(urbanthreads_q4[[#This Row],[Order Date]]) & "-W" & WEEKNUM(urbanthreads_q4[[#This Row],[Order Date]], 2) -> 2024-W53 | AD5: =IF(urbanthreads_q4[[#This Row],[Payment]]="COD","COD","Prepaid") -> Prepaid
A6: UT-100005 | B6: 45566 | C6: CUST_10001 | D6: New | E6: ACC-SCF-OS | F6: Accessories | G6: Silk Scarf | H6: 799 | I6: 3 | J6: 2397 | L6: 0 | M6: UPI | N6: Website | O6: Mumbai | P6: Maharashtra | Q6: Mumbai | R6: 45571 | S6: Delivered | T6: No | W6: Not Applicable | X6: =IF(urbanthreads_q4[[#This Row],[Qty]]>0,"Valid","Invalid") -> Valid | Y6: =urbanthreads_q4[[#This Row],[Total]]*urbanthreads_q4[[#This Row],[Disc %]]/100 -> 0 | Z6: =urbanthreads_q4[[#This Row],[Total]]-urbanthreads_q4[[#This Row],[Disc %]] -> 2397 | AA6: =urbanthreads_q4[[#This Row],[Net revenue]]/urbanthreads_q4[[#This Row],[Total]] -> 1 | AB6: =TEXT(urbanthreads_q4[[#This Row],[Order Date]],"mm-yyyy") -> 10-2024 | AC6: =YEAR(urbanthreads_q4[[#This Row],[Order Date]]) & "-W" & WEEKNUM(urbanthreads_q4[[#This Row],[Order Date]], 2) -> 2024-W40 | AD6: =IF(urbanthreads_q4[[#This Row],[Payment]]="COD","COD","Prepaid") -> Prepaid
A7: UT-100346 | B7: 45657 | C7: CUST_10345 | D7: New | E7: DRS-CNT-S | F7: Dresses | G7: Countdown Dress | H7: 4499 | I7: 1 | J7: 4499 | K7: Dec20 | L7: 20 | M7: Credit Card | N7: Website | O7: Noida | P7: Uttar Pradesh | Q7: Delhi | R7: 45685 | S7: Delivered | T7: Yes | U7: Size Issue | V7: 45713 | W7: Processed | X7: =IF(urbanthreads_q4[[#This Row],[Qty]]>0,"Valid","Invalid") -> Valid | Y7: =urbanthreads_q4[[#This Row],[Total]]*urbanthreads_q4[[#This Row],[Disc %]]/100 -> 899.8 | Z7: =urbanthreads_q4[[#This Row],[Total]]-urbanthreads_q4[[#This Row],[Disc %]] -> 4479 | AA7: =urbanthreads_q4[[#This Row],[Net revenue]]/urbanthreads_q4[[#This Row],[Total]] -> 0.99555457 | AB7: =TEXT(urbanthreads_q4[[#This Row],[Order Date]],"mm-yyyy") -> 12-2024 | AC7: =YEAR(urbanthreads_q4[[#This Row],[Order Date]]) & "-W" & WEEKNUM(urbanthreads_q4[[#This Row],[Order Date]], 2) -> 2024-W53 | AD7: =IF(urbanthreads_q4[[#This Row],[Payment]]="COD","COD","Prepaid") -> Prepaid
A8: UT-100007 | B8: 45567 | C8: CUST_10006 | D8: New | E8: DRS-CAS-M | F8: Dresses | G8: A-Line Dress | H8: 2199 | I8: 1 | J8: 2199 | K8: DIWALI20 | L8: 20 | M8: COD | N8: Website | O8: Pune | P8: Maharashtra | Q8: Mumbai | S8: Cancelled | T8: No | W8: Not Applicable | X8: =IF(urbanthreads_q4[[#This Row],[Qty]]>0,"Valid","Invalid") -> Valid | Y8: =urbanthreads_q4[[#This Row],[Total]]*urbanthreads_q4[[#This Row],[Disc %]]/100 -> 439.8 | Z8: =urbanthreads_q4[[#This Row],[Total]]-urbanthreads_q4[[#This Row],[Disc %]] -> 2179 | AA8: =urbanthreads_q4[[#This Row],[Net revenue]]/urbanthreads_q4[[#This Row],[Total]] -> 0.99090496 | AB8: =TEXT(urbanthreads_q4[[#This Row],[Order Date]],"mm-yyyy") -> 10-2024 | AC8: =YEAR(urbanthreads_q4[[#This Row],[Order Date]]) & "-W" & WEEKNUM(urbanthreads_q4[[#This Row],[Order Date]], 2) -> 2024-W40 | AD8: =IF(urbanthreads_q4[[#This Row],[Payment]]="COD","COD","Prepaid") -> COD
A9: UT-100008 | B9: 45567 | C9: CUST_10007 | D9: New | E9: BOT-TRS-L | F9: Bottoms | G9: Formal Trousers | H9: 2299 | I9: 1 | J9: 2299 | L9: 0 | M9: UPI | N9: Mobile App | O9: Kolkata | P9: West Bengal | Q9: Delhi | R9: 45575 | S9: Delivered | T9: No | W9: Not Applicable | X9: =IF(urbanthreads_q4[[#This Row],[Qty]]>0,"Valid","Invalid") -> Valid | Y9: =urbanthreads_q4[[#This Row],[Total]]*urbanthreads_q4[[#This Row],[Disc %]]/100 -> 0 | Z9: =urbanthreads_q4[[#This Row],[Total]]-urbanthreads_q4[[#This Row],[Disc %]] -> 2299 | AA9: =urbanthreads_q4[[#This Row],[Net revenue]]/urbanthreads_q4[[#This Row],[Total]] -> 1 | AB9: =TEXT(urbanthreads_q4[[#This Row],[Order Date]],"mm-yyyy") -> 10-2024 | AC9: =YEAR(urbanthreads_q4[[#This Row],[Order Date]]) & "-W" & WEEKNUM(urbanthreads_q4[[#This Row],[Order Date]], 2) -> 2024-W40 | AD9: =IF(urbanthreads_q4[[#This Row],[Payment]]="COD","COD","Prepaid") -> Prepaid
A10: UT-100315 | B10: 45649 | C10: CUST_10314 | D10: New | E10: TOP-FLK-L | F10: Tops | G10: Snowflake Top | H10: 2199 | I10: 1 | J10: 2199 | L10: 0 | M10: Debit Card | N10: Instagram Shop | O10: Mumbai | P10: Maharashtra | Q10: Mumbai | R10: 45672 | S10: Delivered | T10: Yes | U10: Damaged in Transit | V10: 45699 | W10: Processed | X10: =IF(urbanthreads_q4[[#This Row],[Qty]]>0,"Valid","Invalid") -> Valid | Y10: =urbanthreads_q4[[#This Row],[Total]]*urbanthreads_q4[[#This Row],[Disc %]]/100 -> 0 | Z10: =urbanthreads_q4[[#This Row],[Total]]-urbanthreads_q4[[#This Row],[Disc %]] -> 2199 | AA10: =urbanthreads_q4[[#This Row],[Net revenue]]/urbanthreads_q4[[#This Row],[Total]] -> 1 | AB10: =TEXT(urbanthreads_q4[[#This Row],[Order Date]],"mm-yyyy") -> 12-2024 | AC10: =YEAR(urbanthreads_q4[[#This Row],[Order Date]]) & "-W" & WEEKNUM(urbanthreads_q4[[#This Row],[Order Date]], 2) -> 2024-W52 | AD10: =IF(urbanthreads_q4[[#This Row],[Payment]]="COD","COD","Prepaid") -> Prepaid
A11: UT-100316 | B11: 45649 | C11: CUST_10315 | D11: New | E11: DRS-SPR-S | F11: Dresses | G11: Sparkle Season Dress | H11: 3799 | I11: 1 | J11: 3799 | K11: Dec20 | L11: 20 | M11: Credit Card | N11: Website | O11: Delhi | P11: Delhi | Q11: Delhi | R11: 45673 | S11: Delivered | T11: Yes | U11: Size Issue | V11: 45701 | W11: Processed | X11: =IF(urbanthreads_q4[[#This Row],[Qty]]>0,"Valid","Invalid") -> Valid | Y11: =urbanthreads_q4[[#This Row],[Total]]*urbanthreads_q4[[#This Row],[Disc %]]/100 -> 759.8 | Z11: =urbanthreads_q4[[#This Row],[Total]]-urbanthreads_q4[[#This Row],[Disc %]] -> 3779 | AA11: =urbanthreads_q4[[#This Row],[Net revenue]]/urbanthreads_q4[[#This Row],[Total]] -> 0.99473546 | AB11: =TEXT(urbanthreads_q4[[#This Row],[Order Date]],"mm-yyyy") -> 12-2024 | AC11: =YEAR(urbanthreads_q4[[#This Row],[Order Date]]) & "-W" & WEEKNUM(urbanthreads_q4[[#This Row],[Order Date]], 2) -> 2024-W52 | AD11: =IF(urbanthreads_q4[[#This Row],[Payment]]="COD","COD","Prepaid") -> Prepaid
A12: UT-100011 | B12: 45568 | C12: CUST_10010 | D12: New | E12: ACC-BAG-OS | F12: Accessories | G12: Tote Bag | H12: 1299 | I12: 2 | J12: 2598 | K12: FLAT10 | L12: 10 | M12: Wallet | N12: Website | O12: Lucknow | P12: Uttar Pradesh | Q12: Delhi | R12: 45575 | S12: Delivered | T12: No | W12: Not Applicable | X12: =IF(urbanthreads_q4[[#This Row],[Qty]]>0,"Valid","Invalid") -> Valid | Y12: =urbanthreads_q4[[#This Row],[Total]]*urbanthreads_q4[[#This Row],[Disc %]]/100 -> 259.8 | Z12: =urbanthreads_q4[[#This Row],[Total]]-urbanthreads_q4[[#This Row],[Disc %]] -> 2588 | AA12: =urbanthreads_q4[[#This Row],[Net revenue]]/urbanthreads_q4[[#This Row],[Total]] -> 0.99615089 | AB12: =TEXT(urbanthreads_q4[[#This Row],[Order Date]],"mm-yyyy") -> 10-2024 | AC12: =YEAR(urbanthreads_q4[[#This Row],[Order Date]]) & "-W" & WEEKNUM(urbanthreads_q4[[#This Row],[Order Date]], 2) -> 2024-W40 | AD12: =IF(urbanthreads_q4[[#This Row],[Payment]]="COD","COD","Prepaid") -> Prepaid
A13: UT-100012 | B13: 45568 | C13: CUST_10011 | D13: New | E13: DRS-PRT-S | F13: Dresses | G13: Party Dress | H13: 3299 | I13: 1 | J13: 3299 | L13: 0 | M13: COD | N13: Mobile App | O13: Chandigarh | P13: Punjab | Q13: Delhi | S13: RTO | T13: No | W13: Not Applicable | X13: =IF(urbanthreads_q4[[#This Row],[Qty]]>0,"Valid","Invalid") -> Valid | Y13: =urbanthreads_q4[[#This Row],[Total]]*urbanthreads_q4[[#This Row],[Disc %]]/100 -> 0 | Z13: =urbanthreads_q4[[#This Row],[Total]]-urbanthreads_q4[[#This Row],[Disc %]] -> 3299 | AA13: =urbanthreads_q4[[#This Row],[Net revenue]]/urbanthreads_q4[[#This Row],[Total]] -> 1 | AB13: =TEXT(urbanthreads_q4[[#This Row],[Order Date]],"mm-yyyy") -> 10-2024 | AC13: =YEAR(urbanthreads_q4[[#This Row],[Order Date]]) & "-W" & WEEKNUM(urbanthreads_q4[[#This Row],[Order Date]], 2) -> 2024-W40 | AD13: =IF(urbanthreads_q4[[#This Row],[Payment]]="COD","COD","Prepaid") -> COD
A14: UT-100013 | B14: 45568 | C14: CUST_10012 | D14: Returning | E14: TOP-SLK-M | F14: Tops | G14: Silk Blouse | H14: 2499 | I14: 1 | J14: 2499 | L14: 0 | M14: Credit Card | N14: Website | O14: Mumbai | P14: Maharashtra | Q14: Mumbai | R14: 45574 | S14: Delivered | T14: No | W14: Not Applicable | X14: =IF(urbanthreads_q4[[#This Row],[Qty]]>0,"Valid","Invalid") -> Valid | Y14: =urbanthreads_q4[[#This Row],[Total]]*urbanthreads_q4[[#This Row],[Disc %]]/100 -> 0 | Z14: =urbanthreads_q4[[#This Row],[Total]]-urbanthreads_q4[[#This Row],[Disc %]] -> 2499 | AA14: =urbanthreads_q4[[#This Row],[Net revenue]]/urbanthreads_q4[[#This Row],[Total]] -> 1 | AB14: =TEXT(urbanthreads_q4[[#This Row],[Order Date]],"mm-yyyy") -> 10-2024 | AC14: =YEAR(urbanthreads_q4[[#This Row],[Order Date]]) & "-W" & WEEKNUM(urbanthreads_q4[[#This Row],[Order Date]], 2) -> 2024-W40 | AD14: =IF(urbanthreads_q4[[#This Row],[Payment]]="COD","COD","Prepaid") -> Prepaid
A15: UT-100318 | B15: 45650 | C15: CUST_10317 | D15: New | E15: OUT-XMS-L | F15: Outerwear | G15: Christmas Coat | H15: 6499 | I15: 1 | J15: 6499 | L15: 0 | M15: COD | N15: Instagram Shop | O15: Noida | P15: Uttar Pradesh | Q15: Delhi | R15: 45674 | S15: Delivered | T15: Yes | U15: Changed Mind | V15: 45702 | W15: Processed | X15: =IF(urbanthreads_q4[[#This Row],[Qty]]>0,"Valid","Invalid") -> Valid | Y15: =urbanthreads_q4[[#This Row],[Total]]*urbanthreads_q4[[#This Row],[Disc %]]/100 -> 0 | Z15: =urbanthreads_q4[[#This Row],[Total]]-urbanthreads_q4[[#This Row],[Disc %]] -> 6499 | AA15: =urbanthreads_q4[[#This Row],[Net revenue]]/urbanthreads_q4[[#This Row],[Total]] -> 1 | AB15: =TEXT(urbanthreads_q4[[#This Row],[Order Date]],"mm-yyyy") -> 12-2024 | AC15: =YEAR(urbanthreads_q4[[#This Row],[Order Date]]) & "-W" & WEEKNUM(urbanthreads_q4[[#This Row],[Order Date]], 2) -> 2024-W52 | AD15: =IF(urbanthreads_q4[[#This Row],[Payment]]="COD","COD","Prepaid") -> COD
A16: UT-100015 | B16: 45568 | C16: CUST_10014 | D16: New | E16: OUT-CRD-L | F16: Outerwear | G16: Knit Cardigan | H16: 2799 | I16: 1 | J16: 2799 | L16: 0 | M16: Debit Card | N16: Mobile App | O16: Bangalore | P16: Karnataka | Q16: Bangalore | R16: 45577 | S16: Delivered | T16: No | W16: Not Applicable | X16: =IF(urbanthreads_q4[[#This Row],[Qty]]>0,"Valid","Invalid") -> Valid | Y16: =urbanthreads_q4[[#This Row],[Total]]*urbanthreads_q4[[#This Row],[Disc %]]/100 -> 0 | Z16: =urbanthreads_q4[[#This Row],[Total]]-urbanthreads_q4[[#This Row],[Disc %]] -> 2799 | AA16: =urbanthreads_q4[[#This Row],[Net revenue]]/urbanthreads_q4[[#This Row],[Total]] -> 1 | AB16: =TEXT(urbanthreads_q4[[#This Row],[Order Date]],"mm-yyyy") -> 10-2024 | AC16: =YEAR(urbanthreads_q4[[#This Row],[Order Date]]) & "-W" & WEEKNUM(urbanthreads_q4[[#This Row],[Order Date]], 2) -> 2024-W40 | AD16: =IF(urbanthreads_q4[[#This Row],[Payment]]="COD","COD","Prepaid") -> Prepaid
A17: UT-100320 | B17: 45650 | C17: CUST_10319 | D17: New | E17: TOP-RDR-M | F17: Tops | G17: Reindeer Top | H17: 1799 | I17: 1 | J17: 1799 | L17: 0 | M17: Debit Card | N17: Mobile App | O17: Indore | P17: Madhya Pradesh | Q17: Mumbai | R17: 45674 | S17: Delivered | T17: Yes | U17: Quality Defect | V17: 45701 | W17: Processed | X17: =IF(urbanthreads_q4[[#This Row],[Qty]]>0,"Valid","Invalid") -> Valid | Y17: =urbanthreads_q4[[#This Row],[Total]]*urbanthreads_q4[[#This Row],[Disc %]]/100 -> 0 | Z17: =urbanthreads_q4[[#This Row],[Total]]-urbanthreads_q4[[#This Row],[Disc %]] -> 1799 | AA17: =urbanthreads_q4[[#This Row],[Net revenue]]/urbanthreads_q4[[#This Row],[Total]] -> 1 | AB17: =TEXT(urbanthreads_q4[[#This Row],[Order Date]],"mm-yyyy") -> 12-2024 | AC17: =YEAR(urbanthreads_q4[[#This Row],[Order Date]]) & "-W" & WEEKNUM(urbanthreads_q4[[#This Row],[Order Date]], 2) -> 2024-W52 | AD17: =IF(urbanthreads_q4[[#This Row],[Payment]]="COD","COD","Prepaid") -> Prepaid
A18: UT-100017 | B18: 45569 | C18: CUST_10016 | D18: New | E18: TOP-CRP-XS | F18: Tops | G18: Crop Top | H18: 999 | I18: 1 | J18: 999 | K18: FIRST15 | L18: 15 | M18: UPI | N18: Mobile App | O18: Gurgaon | P18: Haryana | Q18: Delhi | R18: 45577 | S18: Delivered | T18: No | W18: Not Applicable | X18: =IF(urbanthreads_q4[[#This Row],[Qty]]>0,"Valid","Invalid") -> Valid | Y18: =urbanthreads_q4[[#This Row],[Total]]*urbanthreads_q4[[#This Row],[Disc %]]/100 -> 149.85 | Z18: =urbanthreads_q4[[#This Row],[Total]]-urbanthreads_q4[[#This Row],[Disc %]] -> 984 | AA18: =urbanthreads_q4[[#This Row],[Net revenue]]/urbanthreads_q4[[#This Row],[Total]] -> 0.98498498 | AB18: =TEXT(urbanthreads_q4[[#This Row],[Order Date]],"mm-yyyy") -> 10-2024 | AC18: =YEAR(urbanthreads_q4[[#This Row],[Order Date]]) & "-W" & WEEKNUM(urbanthreads_q4[[#This Row],[Order Date]], 2) -> 2024-W40 | AD18: =IF(urbanthreads_q4[[#This Row],[Payment]]="COD","COD","Prepaid") -> Prepaid
A19: UT-100018 | B19: 45569 | C19: CUST_10017 | D19: New | E19: DRS-MAX-M | F19: Dresses | G19: Maxi Dress | H19: 2899 | I19: 1 | J19: 2899 | L19: 0 | M19: Credit Card | N19: Website | O19: Indore | P19: Madhya Pradesh | Q19: Mumbai | R19: 45579 | S19: Delivered | T19: No | W19: Not Applicable | X19: =IF(urbanthreads_q4[[#This Row],[Qty]]>0,"Valid","Invalid") -> Valid | Y19: =urbanthreads_q4[[#This Row],[Total]]*urbanthreads_q4[[#This Row],[Disc %]]/100 -> 0 | Z19: =urbanthreads_q4[[#This Row],[Total]]-urbanthreads_q4[[#This Row],[Disc %]] -> 2899 | AA19: =urbanthreads_q4[[#This Row],[Net revenue]]/urbanthreads_q4[[#This Row],[Total]] -> 1 | AB19: =TEXT(urbanthreads_q4[[#This Row],[Order Date]],"mm-yyyy") -> 10-2024 | AC19: =YEAR(urbanthreads_q4[[#This Row],[Order Date]]) & "-W" & WEEKNUM(urbanthreads_q4[[#This Row],[Order Date]], 2) -> 2024-W40 | AD19: =IF(urbanthreads_q4[[#This Row],[Payment]]="COD","COD","Prepaid") -> Prepaid
A20: UT-100321 | B20: 45650 | C20: CUST_10320 | D20: New | E20: DRS-STR-L | F20: Dresses | G20: Star Bright Dress | H20: 4299 | I20: 1 | J20: 4299 | L20: 0 | M20: Credit Card | N20: Instagram Shop | O20: Surat | P20: Gujarat | Q20: Mumbai | R20: 45675 | S20: Delivered | T20: Yes | U20: Size Issue | V20: 45703 | W20: Processed | X20: =IF(urbanthreads_q4[[#This Row],[Qty]]>0,"Valid","Invalid") -> Valid | Y20: =urbanthreads_q4[[#This Row],[Total]]*urbanthreads_q4[[#This Row],[Disc %]]/100 -> 0 | Z20: =urbanthreads_q4[[#This Row],[Total]]-urbanthreads_q4[[#This Row],[Disc %]] -> 4299 | AA20: =urbanthreads_q4[[#This Row],[Net revenue]]/urbanthreads_q4[[#This Row],[Total]] -> 1 | AB20: =TEXT(urbanthreads_q4[[#This Row],[Order Date]],"mm-yyyy") -> 12-2024 | AC20: =YEAR(urbanthreads_q4[[#This Row],[Order Date]]) & "-W" & WEEKNUM(urbanthreads_q4[[#This Row],[Order Date]], 2) -> 2024-W52 | AD20: =IF(urbanthreads_q4[[#This Row],[Payment]]="COD","COD","Prepaid") -> Prepaid
A21: UT-100020 | B21: 45570 | C21: CUST_10019 | D21: New | E21: OUT-VST-S | F21: Outerwear | G21: Puffer Vest | H21: 3999 | I21: 1 | J21: 3999 | K21: DIWALI20 | L21: 20 | M21: COD | N21: Website | O21: Patna | P21: Bihar | Q21: Delhi | S21: RTO | T21: No | W21: Not Applicable | X21: =IF(urbanthreads_q4[[#This Row],[Qty]]>0,"Valid","Invalid") -> Valid | Y21: =urbanthreads_q4[[#This Row],[Total]]*urbanthreads_q4[[#This Row],[Disc %]]/100 -> 799.8 | Z21: =urbanthreads_q4[[#This Row],[Total]]-urbanthreads_q4[[#This Row],[Disc %]] -> 3979 | AA21: =urbanthreads_q4[[#This Row],[Net revenue]]/urbanthreads_q4[[#This Row],[Total]] -> 0.99499875 | AB21: =TEXT(urbanthreads_q4[[#This Row],[Order Date]],"mm-yyyy") -> 10-2024 | AC21: =YEAR(urbanthreads_q4[[#This Row],[Order Date]]) & "-W" & WEEKNUM(urbanthreads_q4[[#This Row],[Order Date]], 2) -> 2024-W40 | AD21: =IF(urbanthreads_q4[[#This Row],[Payment]]="COD","COD","Prepaid") -> COD
A22: UT-100021 | B22: 45570 | C22: CUST_10020 | D22: New | E22: TOP-TUN-L | F22: Tops | G22: Tunic Top | H22: 1699 | I22: 1 | J22: 1699 | L22: 0 | M22: UPI | N22: Mobile App | O22: Bhopal | P22: Madhya Pradesh | Q22: Mumbai | R22: 45580 | S22: Delivered | T22: No | W22: Not Applicable | X22: =IF(urbanthreads_q4[[#This Row],[Qty]]>0,"Valid","Invalid") -> Valid | Y22: =urbanthreads_q4[[#This Row],[Total]]*urbanthreads_q4[[#This Row],[Disc %]]/100 -> 0 | Z22: =urbanthreads_q4[[#This Row],[Total]]-urbanthreads_q4[[#This Row],[Disc %]] -> 1699 | AA22: =urbanthreads_q4[[#This Row],[Net revenue]]/urbanthreads_q4[[#This Row],[Total]] -> 1 | AB22: =TEXT(urbanthreads_q4[[#This Row],[Order Date]],"mm-yyyy") -> 10-2024 | AC22: =YEAR(urbanthreads_q4[[#This Row],[Order Date]]) & "-W" & WEEKNUM(urbanthreads_q4[[#This Row],[Order Date]], 2) -> 2024-W40 | AD22: =IF(urbanthreads_q4[[#This Row],[Payment]]="COD","COD","Prepaid") -> Prepaid
A23: UT-100323 | B23: 45651 | C23: CUST_10322 | D23: New | E23: OUT-JOL-M | F23: Outerwear | G23: Jolly Jacket | H23: 4999 | I23: 1 | J23: 4999 | L23: 0 | M23: COD | N23: Mobile App | O23: Bhopal | P23: Madhya Pradesh | Q23: Mumbai | R23: 45676 | S23: Delivered | T23: Yes | U23: Wrong Item | V23: 45704 | W23: Processed | X23: =IF(urbanthreads_q4[[#This Row],[Qty]]>0,"Valid","Invalid") -> Valid | Y23: =urbanthreads_q4[[#This Row],[Total]]*urbanthreads_q4[[#This Row],[Disc %]]/100 -> 0 | Z23: =urbanthreads_q4[[#This Row],[Total]]-urbanthreads_q4[[#This Row],[Disc %]] -> 4999 | AA23: =urbanthreads_q4[[#This Row],[Net revenue]]/urbanthreads_q4[[#This Row],[Total]] -> 1 | AB23: =TEXT(urbanthreads_q4[[#This Row],[Order Date]],"mm-yyyy") -> 12-2024 | AC23: =YEAR(urbanthreads_q4[[#This Row],[Order Date]]) & "-W" & WEEKNUM(urbanthreads_q4[[#This Row],[Order Date]], 2) -> 2024-W52 | AD23: =IF(urbanthreads_q4[[#This Row],[Payment]]="COD","COD","Prepaid") -> COD
A24: UT-100023 | B24: 45570 | C24: CUST_10022 | D24: New | E24: ACC-BLT-M | F24: Accessories | G24: Leather Belt | H24: 899 | I24: 1 | J24: 899 | K24: FLAT10 | L24: 10 | M24: Debit Card | N24: Mobile App | O24: Coimbatore | P24: Tamil Nadu | Q24: Bangalore | R24: 45582 | S24: Delivered | T24: No | W24: Not Applicable | X24: =IF(urbanthreads_q4[[#This Row],[Qty]]>0,"Valid","Invalid") -> Valid | Y24: =urbanthreads_q4[[#This Row],[Total]]*urbanthreads_q4[[#This Row],[Disc %]]/100 -> 89.9 | Z24: =urbanthreads_q4[[#This Row],[Total]]-urbanthreads_q4[[#This Row],[Disc %]] -> 889 | AA24: =urbanthreads_q4[[#This Row],[Net revenue]]/urbanthreads_q4[[#This Row],[Total]] -> 0.98887653 | AB24: =TEXT(urbanthreads_q4[[#This Row],[Order Date]],"mm-yyyy") -> 10-2024 | AC24: =YEAR(urbanthreads_q4[[#This Row],[Order Date]]) & "-W" & WEEKNUM(urbanthreads_q4[[#This Row],[Order Date]], 2) -> 2024-W40 | AD24: =IF(urbanthreads_q4[[#This Row],[Payment]]="COD","COD","Prepaid") -> Prepaid
A25: UT-100325 | B25: 45651 | C25: CUST_10324 | D25: New | E25: TOP-HLY-L | F25: Tops | G25: Holly Top | H25: 2099 | I25: 1 | J25: 2099 | K25: Dec20 | L25: 20 | M25: Debit Card | N25: Website | O25: Coimbatore | P25: Tamil Nadu | Q25: Bangalore | R25: 45676 | S25: Delivered | T25: Yes | U25: Damaged in Transit | V25: 45703 | W25: Processed | X25: =IF(urbanthreads_q4[[#This Row],[Qty]]>0,"Valid","Invalid") -> Valid | Y25: =urbanthreads_q4[[#This Row],[Total]]*urbanthreads_q4[[#This Row],[Disc %]]/100 -> 419.8 | Z25: =urbanthreads_q4[[#This Row],[Total]]-urbanthreads_q4[[#This Row],[Disc %]] -> 2079 | AA25: =urbanthreads_q4[[#This Row],[Net revenue]]/urbanthreads_q4[[#This Row],[Total]] -> 0.99047165 | AB25: =TEXT(urbanthreads_q4[[#This Row],[Order Date]],"mm-yyyy") -> 12-2024 | AC25: =YEAR(urbanthreads_q4[[#This Row],[Order Date]]) & "-W" & WEEKNUM(urbanthreads_q4[[#This Row],[Order Date]], 2) -> 2024-W52 | AD25: =IF(urbanthreads_q4[[#This Row],[Payment]]="COD","COD","Prepaid") -> Prepaid
A26: UT-100025 | B26: 45571 | C26: CUST_10024 | D26: New | E26: TOP-PLO-L | F26: Tops | G26: Polo Shirt | H26: 1799 | I26: 2 | J26: 3598 | L26: 0 | M26: UPI | N26: Website | O26: Vizag | P26: Andhra Pradesh | Q26: Bangalore | R26: 45582 | S26: Delivered | T26: No | W26: Not Applicable | X26: =IF(urbanthreads_q4[[#This Row],[Qty]]>0,"Valid","Invalid") -> Valid | Y26: =urbanthreads_q4[[#This Row],[Total]]*urbanthreads_q4[[#This Row],[Disc %]]/100 -> 0 | Z26: =urbanthreads_q4[[#This Row],[Total]]-urbanthreads_q4[[#This Row],[Disc %]] -> 3598 | AA26: =urbanthreads_q4[[#This Row],[Net revenue]]/urbanthreads_q4[[#This Row],[Total]] -> 1 | AB26: =TEXT(urbanthreads_q4[[#This Row],[Order Date]],"mm-yyyy") -> 10-2024 | AC26: =YEAR(urbanthreads_q4[[#This Row],[Order Date]]) & "-W" & WEEKNUM(urbanthreads_q4[[#This Row],[Order Date]], 2) -> 2024-W40 | AD26: =IF(urbanthreads_q4[[#This Row],[Payment]]="COD","COD","Prepaid") -> Prepaid
A27: UT-100026 | B27: 45571 | C27: CUST_10025 | D27: New | E27: DRS-WRK-M | F27: Dresses | G27: Work Dress | H27: 2699 | I27: 1 | J27: 2699 | L27: 0 | M27: Credit Card | N27: Mobile App | O27: Thiruvananthapuram | P27: Kerala | Q27: Bangalore | R27: 45583 | S27: Delivered | T27: No | W27: Not Applicable | X27: =IF(urbanthreads_q4[[#This Row],[Qty]]>0,"Valid","Invalid") -> Valid | Y27: =urbanthreads_q4[[#This Row],[Total]]*urbanthreads_q4[[#This Row],[Disc %]]/100 -> 0 | Z27: =urbanthreads_q4[[#This Row],[Total]]-urbanthreads_q4[[#This Row],[Disc %]] -> 2699 | AA27: =urbanthreads_q4[[#This Row],[Net revenue]]/urbanthreads_q4[[#This Row],[Total]] -> 1 | AB27: =TEXT(urbanthreads_q4[[#This Row],[Order Date]],"mm-yyyy") -> 10-2024 | AC27: =YEAR(urbanthreads_q4[[#This Row],[Order Date]]) & "-W" & WEEKNUM(urbanthreads_q4[[#This Row],[Order Date]], 2) -> 2024-W40 | AD27: =IF(urbanthreads_q4[[#This Row],[Payment]]="COD","COD","Prepaid") -> Prepaid
A28: UT-100326 | B28: 45652 | C28: CUST_10325 | D28: New | E28: DRS-BOX-S | F28: Dresses | G28: Boxing Day Dress | H28: 2999 | I28: 1 | J28: 2999 | L28: 0 | M28: Credit Card | N28: Mobile App | O28: Kochi | P28: Kerala | Q28: Bangalore | R28: 45677 | S28: Delivered | T28: Yes | U28: Size Issue | V28: 45705 | W28: Processed | X28: =IF(urbanthreads_q4[[#This Row],[Qty]]>0,"Valid","Invalid") -> Valid | Y28: =urbanthreads_q4[[#This Row],[Total]]*urbanthreads_q4[[#This Row],[Disc %]]/100 -> 0 | Z28: =urbanthreads_q4[[#This Row],[Total]]-urbanthreads_q4[[#This Row],[Disc %]] -> 2999 | AA28: =urbanthreads_q4[[#This Row],[Net revenue]]/urbanthreads_q4[[#This Row],[Total]] -> 1 | AB28: =TEXT(urbanthreads_q4[[#This Row],[Order Date]],"mm-yyyy") -> 12-2024 | AC28: =YEAR(urbanthreads_q4[[#This Row],[Order Date]]) & "-W" & WEEKNUM(urbanthreads_q4[[#This Row],[Order Date]], 2) -> 2024-W52 | AD28: =IF(urbanthreads_q4[[#This Row],[Payment]]="COD","COD","Prepaid") -> Prepaid
A29: UT-100028 | B29: 45572 | C29: CUST_10027 | D29: New | E29: ACC-HAT-OS | F29: Accessories | G29: Fedora Hat | H29: 1099 | I29: 1 | J29: 1099 | L29: 0 | M29: UPI | N29: Instagram Shop | O29: Vadodara | P29: Gujarat | Q29: Mumbai | R29: 45585 | S29: Delivered | T29: No | W29: Not Applicable | X29: =IF(urbanthreads_q4[[#This Row],[Qty]]>0,"Valid","Invalid") -> Valid | Y29: =urbanthreads_q4[[#This Row],[Total]]*urbanthreads_q4[[#This Row],[Disc %]]/100 -> 0 | Z29: =urbanthreads_q4[[#This Row],[Total]]-urbanthreads_q4[[#This Row],[Disc %]] -> 1099 | AA29: =urbanthreads_q4[[#This Row],[Net revenue]]/urbanthreads_q4[[#This Row],[Total]] -> 1 | AB29: =TEXT(urbanthreads_q4[[#This Row],[Order Date]],"mm-yyyy") -> 10-2024 | AC29: =YEAR(urbanthreads_q4[[#This Row],[Order Date]]) & "-W" & WEEKNUM(urbanthreads_q4[[#This Row],[Order Date]], 2) -> 2024-W41 | AD29: =IF(urbanthreads_q4[[#This Row],[Payment]]="COD","COD","Prepaid") -> Prepaid
A30: UT-100029 | B30: 45572 | C30: CUST_10028 | D30: New | E30: TOP-DNM-M | F30: Tops | G30: Denim Shirt | H30: 1899 | I30: 1 | J30: 1899 | L30: 0 | M30: COD | N30: Mobile App | O30: Rajkot | P30: Gujarat | Q30: Mumbai | S30: RTO | T30: No | W30: Not Applicable | X30: =IF(urbanthreads_q4[[#This Row],[Qty]]>0,"Valid","Invalid") -> Valid | Y30: =urbanthreads_q4[[#This Row],[Total]]*urbanthreads_q4[[#This Row],[Disc %]]/100 -> 0 | Z30: =urbanthreads_q4[[#This Row],[Total]]-urbanthreads_q4[[#This Row],[Disc %]] -> 1899 | AA30: =urbanthreads_q4[[#This Row],[Net revenue]]/urbanthreads_q4[[#This Row],[Total]] -> 1 | AB30: =TEXT(urbanthreads_q4[[#This Row],[Order Date]],"mm-yyyy") -> 10-2024 | AC30: =YEAR(urbanthreads_q4[[#This Row],[Order Date]]) & "-W" & WEEKNUM(urbanthreads_q4[[#This Row],[Order Date]], 2) -> 2024-W41 | AD30: =IF(urbanthreads_q4[[#This Row],[Payment]]="COD","COD","Prepaid") -> COD
A31: UT-100030 | B31: 45572 | C31: CUST_10029 | D31: New | E31: BOT-CRG-L | F31: Bottoms | G31: Cargo Pants | H31: 2199 | I31: 1 | J31: 2199 | K31: DIWALI20 | L31: 20 | M31: Credit Card | N31: Website | O31: Kanpur | P31: Uttar Pradesh | Q31: Delhi | R31: 45585 | S31: Delivered | T31: No | W31: Not Applicable | X31: =IF(urbanthreads_q4[[#This Row],[Qty]]>0,"Valid","Invalid") -> Valid | Y31: =urbanthreads_q4[[#This Row],[Total]]*urbanthreads_q4[[#This Row],[Disc %]]/100 -> 439.8 | Z31: =urbanthreads_q4[[#This Row],[Total]]-urbanthreads_q4[[#This Row],[Disc %]] -> 2179 | AA31: =urbanthreads_q4[[#This Row],[Net revenue]]/urbanthreads_q4[[#This Row],[Total]] -> 0.99090496 | AB31: =TEXT(urbanthreads_q4[[#This Row],[Order Date]],"mm-yyyy") -> 10-2024 | AC31: =YEAR(urbanthreads_q4[[#This Row],[Order Date]]) & "-W" & WEEKNUM(urbanthreads_q4[[#This Row],[Order Date]], 2) -> 2024-W41 | AD31: =IF(urbanthreads_q4[[#This Row],[Payment]]="COD","COD","Prepaid") -> Prepaid
A32: UT-100328 | B32: 45652 | C32: CUST_10327 | D32: New | E32: OUT-SAL-L | F32: Outerwear | G32: Sale Special Coat | H32: 5999 | I32: 1 | J32: 5999 | K32: Dec20 | L32: 20 | M32: COD | N32: Website | O32: Thiruvananthapuram | P32: Kerala | Q32: Bangalore | R32: 45678 | S32: Delivered | T32: Yes | U32: Changed Mind | V32: 45706 | W32: Processed | X32: =IF(urbanthreads_q4[[#This Row],[Qty]]>0,"Valid","Invalid") -> Valid | Y32: =urbanthreads_q4[[#This Row],[Total]]*urbanthreads_q4[[#This Row],[Disc %]]/100 -> 1199.8 | Z32: =urbanthreads_q4[[#This Row],[Total]]-urbanthreads_q4[[#This Row],[Disc %]] -> 5979 | AA32: =urbanthreads_q4[[#This Row],[Net revenue]]/urbanthreads_q4[[#This Row],[Total]] -> 0.99666611 | AB32: =TEXT(urbanthreads_q4[[#This Row],[Order Date]],"mm-yyyy") -> 12-2024 | AC32: =YEAR(urbanthreads_q4[[#This Row],[Order Date]]) & "-W" & WEEKNUM(urbanthreads_q4[[#This Row],[Order Date]], 2) -> 2024-W52 | AD32: =IF(urbanthreads_q4[[#This Row],[Payment]]="COD","COD","Prepaid") -> COD
A33: UT-100032 | B33: 45573 | C33: CUST_10031 | D33: New | E33: TOP-BAS-M | F33: Tops | G33: Basic Tank | H33: 899 | I33: 2 | J33: 1798 | L33: 0 | M33: UPI | N33: Website | O33: Delhi | P33: Delhi | Q33: Delhi | R33: 45579 | S33: Delivered | T33: No | W33: Not Applicable | X33: =IF(urbanthreads_q4[[#This Row],[Qty]]>0,"Valid","Invalid") -> Valid | Y33: =urbanthreads_q4[[#This Row],[Total]]*urbanthreads_q4[[#This Row],[Disc %]]/100 -> 0 | Z33: =urbanthreads_q4[[#This Row],[Total]]-urbanthreads_q4[[#This Row],[Disc %]] -> 1798 | AA33: =urbanthreads_q4[[#This Row],[Net revenue]]/urbanthreads_q4[[#This Row],[Total]] -> 1 | AB33: =TEXT(urbanthreads_q4[[#This Row],[Order Date]],"mm-yyyy") -> 10-2024 | AC33: =YEAR(urbanthreads_q4[[#This Row],[Order Date]]) & "-W" & WEEKNUM(urbanthreads_q4[[#This Row],[Order Date]], 2) -> 2024-W41 | AD33: =IF(urbanthreads_q4[[#This Row],[Payment]]="COD","COD","Prepaid") -> Prepaid
A34: UT-100329 | B34: 45652 | C34: CUST_10328 | D34: Returning | E34: ACC-DIS-OS | F34: Accessories | G34: Discount Find Bag | H34: 1299 | I34: 1 | J34: 1299 | L34: 0 | M34: Wallet | N34: Mobile App | O34: Mysore | P34: Karnataka | Q34: Bangalore | R34: 45677 | S34: Delivered | T34: Yes | U34: Quality Defect | V34: 45704 | W34: Processed | X34: =IF(urbanthreads_q4[[#This Row],[Qty]]>0,"Valid","Invalid") -> Valid | Y34: =urbanthreads_q4[[#This Row],[Total]]*urbanthreads_q4[[#This Row],[Disc %]]/100 -> 0 | Z34: =urbanthreads_q4[[#This Row],[Total]]-urbanthreads_q4[[#This Row],[Disc %]] -> 1299 | AA34: =urbanthreads_q4[[#This Row],[Net revenue]]/urbanthreads_q4[[#This Row],[Total]] -> 1 | AB34: =TEXT(urbanthreads_q4[[#This Row],[Order Date]],"mm-yyyy") -> 12-2024 | AC34: =YEAR(urbanthreads_q4[[#This Row],[Order Date]]) & "-W" & WEEKNUM(urbanthreads_q4[[#This Row],[Order Date]], 2) -> 2024-W52 | AD34: =IF(urbanthreads_q4[[#This Row],[Payment]]="COD","COD","Prepaid") -> Prepaid
A35: UT-100034 | B35: 45573 | C35: CUST_10033 | D35: Returning | E35: ACC-WCH-OS | F35: Accessories | G35: Fashion Watch | H35: 2999 | I35: 1 | J35: 2999 | L35: 0 | M35: Credit Card | N35: Mobile App | O35: Chennai | P35: Tamil Nadu | Q35: Bangalore | R35: 45580 | S35: Delivered | T35: No | W35: Not Applicable | X35: =IF(urbanthreads_q4[[#This Row],[Qty]]>0,"Valid","Invalid") -> Valid | Y35: =urbanthreads_q4[[#This Row],[Total]]*urbanthreads_q4[[#This Row],[Disc %]]/100 -> 0 | Z35: =urbanthreads_q4[[#This Row],[Total]]-urbanthreads_q4[[#This Row],[Disc %]] -> 2999 | AA35: =urbanthreads_q4[[#This Row],[Net revenue]]/urbanthreads_q4[[#This Row],[Total]] -> 1 | AB35: =TEXT(urbanthreads_q4[[#This Row],[Order Date]],"mm-yyyy") -> 10-2024 | AC35: =YEAR(urbanthreads_q4[[#This Row],[Order Date]]) & "-W" & WEEKNUM(urbanthreads_q4[[#This Row],[Order Date]], 2) -> 2024-W41 | AD35: =IF(urbanthreads_q4[[#This Row],[Payment]]="COD","COD","Prepaid") -> Prepaid
A36: UT-100331 | B36: 45653 | C36: CUST_10330 | D36: New | E36: DRS-END-L | F36: Dresses | G36: Year End Dress | H36: 3499 | I36: 1 | J36: 3499 | K36: Dec20 | L36: 20 | M36: Credit Card | N36: Website | O36: Rajkot | P36: Gujarat | Q36: Mumbai | R36: 45679 | S36: Delivered | T36: Yes | U36: Size Issue | V36: 45707 | W36: Processed | X36: =IF(urbanthreads_q4[[#This Row],[Qty]]>0,"Valid","Invalid") -> Valid | Y36: =urbanthreads_q4[[#This Row],[Total]]*urbanthreads_q4[[#This Row],[Disc %]]/100 -> 699.8 | Z36: =urbanthreads_q4[[#This Row],[Total]]-urbanthreads_q4[[#This Row],[Disc %]] -> 3479 | AA36: =urbanthreads_q4[[#This Row],[Net revenue]]/urbanthreads_q4[[#This Row],[Total]] -> 0.99428408 | AB36: =TEXT(urbanthreads_q4[[#This Row],[Order Date]],"mm-yyyy") -> 12-2024 | AC36: =YEAR(urbanthreads_q4[[#This Row],[Order Date]]) & "-W" & WEEKNUM(urbanthreads_q4[[#This Row],[Order Date]], 2) -> 2024-W52 | AD36: =IF(urbanthreads_q4[[#This Row],[Payment]]="COD","COD","Prepaid") -> Prepaid
A37: UT-100036 | B37: 45574 | C37: CUST_10035 | D37: New | E37: DRS-SUN-M | F37: Dresses | G37: Sundress | H37: 1999 | I37: 1 | J37: 1999 | K37: DIWALI20 | L37: 20 | M37: Wallet | N37: Mobile App | O37: Pune | P37: Maharashtra | Q37: Mumbai | R37: 45581 | S37: Delivered | T37: No | W37: Not Applicable | X37: =IF(urbanthreads_q4[[#This Row],[Qty]]>0,"Valid","Invalid") -> Valid | Y37: =urbanthreads_q4[[#This Row],[Total]]*urbanthreads_q4[[#This Row],[Disc %]]/100 -> 399.8 | Z37: =urbanthreads_q4[[#This Row],[Total]]-urbanthreads_q4[[#This Row],[Disc %]] -> 1979 | AA37: =urbanthreads_q4[[#This Row],[Net revenue]]/urbanthreads_q4[[#This Row],[Total]] -> 0.989995 | AB37: =TEXT(urbanthreads_q4[[#This Row],[Order Date]],"mm-yyyy") -> 10-2024 | AC37: =YEAR(urbanthreads_q4[[#This Row],[Order Date]]) & "-W" & WEEKNUM(urbanthreads_q4[[#This Row],[Order Date]], 2) -> 2024-W41 | AD37: =IF(urbanthreads_q4[[#This Row],[Payment]]="COD","COD","Prepaid") -> Prepaid
A38: UT-100333 | B38: 45653 | C38: CUST_10332 | D38: New | E38: OUT-LST-M | F38: Outerwear | G38: Last Chance Jacket | H38: 4599 | I38: 1 | J38: 4599 | L38: 0 | M38: COD | N38: Instagram Shop | O38: Mumbai | P38: Maharashtra | Q38: Mumbai | R38: 45680 | S38: Delivered | T38: Yes | U38: Wrong Item | V38: 45708 | W38: Processed | X38: =IF(urbanthreads_q4[[#This Row],[Qty]]>0,"Valid","Invalid") -> Valid | Y38: =urbanthreads_q4[[#This Row],[Total]]*urbanthreads_q4[[#This Row],[Disc %]]/100 -> 0 | Z38: =urbanthreads_q4[[#This Row],[Total]]-urbanthreads_q4[[#This Row],[Disc %]] -> 4599 | AA38: =urbanthreads_q4[[#This Row],[Net revenue]]/urbanthreads_q4[[#This Row],[Total]] -> 1 | AB38: =TEXT(urbanthreads_q4[[#This Row],[Order Date]],"mm-yyyy") -> 12-2024 | AC38: =YEAR(urbanthreads_q4[[#This Row],[Order Date]]) & "-W" & WEEKNUM(urbanthreads_q4[[#This Row],[Order Date]], 2) -> 2024-W52 | AD38: =IF(urbanthreads_q4[[#This Row],[Payment]]="COD","COD","Prepaid") -> COD
A39: UT-100038 | B39: 45574 | C39: CUST_10037 | D39: Returning | E39: OUT-LTH-M | F39: Outerwear | G39: Leather Jacket | H39: 7999 | I39: 1 | J39: 7999 | L39: 0 | M39: Credit Card | N39: Website | O39: Jaipur | P39: Rajasthan | Q39: Delhi | R39: 45583 | S39: Delivered | T39: No | W39: Not Applicable | X39: =IF(urbanthreads_q4[[#This Row],[Qty]]>0,"Valid","Invalid") -> Valid | Y39: =urbanthreads_q4[[#This Row],[Total]]*urbanthreads_q4[[#This Row],[Disc %]]/100 -> 0 | Z39: =urbanthreads_q4[[#This Row],[Total]]-urbanthreads_q4[[#This Row],[Disc %]] -> 7999 | AA39: =urbanthreads_q4[[#This Row],[Net revenue]]/urbanthreads_q4[[#This Row],[Total]] -> 1 | AB39: =TEXT(urbanthreads_q4[[#This Row],[Order Date]],"mm-yyyy") -> 10-2024 | AC39: =YEAR(urbanthreads_q4[[#This Row],[Order Date]]) & "-W" & WEEKNUM(urbanthreads_q4[[#This Row],[Order Date]], 2) -> 2024-W41 | AD39: =IF(urbanthreads_q4[[#This Row],[Payment]]="COD","COD","Prepaid") -> Prepaid
A40: UT-100039 | B40: 45574 | C40: CUST_10038 | D40: New | E40: ACC-SNG-OS | F40: Accessories | G40: Sunglasses | H40: 1499 | I40: 1 | J40: 1499 | K40: FLAT10 | L40: 10 | M40: Debit Card | N40: Mobile App | O40: Lucknow | P40: Uttar Pradesh | Q40: Delhi | R40: 45582 | S40: Delivered | T40: No | W40: Not Applicable | X40: =IF(urbanthreads_q4[[#This Row],[Qty]]>0,"Valid","Invalid") -> Valid | Y40: =urbanthreads_q4[[#This Row],[Total]]*urbanthreads_q4[[#This Row],[Disc %]]/100 -> 149.9 | Z40: =urbanthreads_q4[[#This Row],[Total]]-urbanthreads_q4[[#This Row],[Disc %]] -> 1489 | AA40: =urbanthreads_q4[[#This Row],[Net revenue]]/urbanthreads_q4[[#This Row],[Total]] -> 0.99332889 | AB40: =TEXT(urbanthreads_q4[[#This Row],[Order Date]],"mm-yyyy") -> 10-2024 | AC40: =YEAR(urbanthreads_q4[[#This Row],[Order Date]]) & "-W" & WEEKNUM(urbanthreads_q4[[#This Row],[Order Date]], 2) -> 2024-W41 | AD40: =IF(urbanthreads_q4[[#This Row],[Payment]]="COD","COD","Prepaid") -> Prepaid
A41: UT-100335 | B41: 45654 | C41: CUST_10334 | D41: New | E41: TOP-BYE-L | F41: Tops | G41: Goodbye 2024 Top | H41: 1899 | I41: 1 | J41: 1899 | L41: 0 | M41: Debit Card | N41: Mobile App | O41: Kolkata | P41: West Bengal | Q41: Delhi | R41: 45680 | S41: Delivered | T41: Yes | U41: Damaged in Transit | V41: 45707 | W41: Processed | X41: =IF(urbanthreads_q4[[#This Row],[Qty]]>0,"Valid","Invalid") -> Valid | Y41: =urbanthreads_q4[[#This Row],[Total]]*urbanthreads_q4[[#This Row],[Disc %]]/100 -> 0 | Z41: =urbanthreads_q4[[#This Row],[Total]]-urbanthreads_q4[[#This Row],[Disc %]] -> 1899 | AA41: =urbanthreads_q4[[#This Row],[Net revenue]]/urbanthreads_q4[[#This Row],[Total]] -> 1 | AB41: =TEXT(urbanthreads_q4[[#This Row],[Order Date]],"mm-yyyy") -> 12-2024 | AC41: =YEAR(urbanthreads_q4[[#This Row],[Order Date]]) & "-W" & WEEKNUM(urbanthreads_q4[[#This Row],[Order Date]], 2) -> 2024-W52 | AD41: =IF(urbanthreads_q4[[#This Row],[Payment]]="COD","COD","Prepaid") -> Prepaid
A42: UT-100041 | B42: 45575 | C42: CUST_10040 | D42: New | E42: DRS-BDC-S | F42: Dresses | G42: Bodycon Dress | H42: 2299 | I42: 1 | J42: 2299 | L42: 0 | M42: UPI | N42: Instagram Shop | O42: Mumbai | P42: Maharashtra | Q42: Mumbai | R42: 45583 | S42: Delivered | T42: No | W42: Not Applicable | X42: =IF(urbanthreads_q4[[#This Row],[Qty]]>0,"Valid","Invalid") -> Valid | Y42: =urbanthreads_q4[[#This Row],[Total]]*urbanthreads_q4[[#This Row],[Disc %]]/100 -> 0 | Z42: =urbanthreads_q4[[#This Row],[Total]]-urbanthreads_q4[[#This Row],[Disc %]] -> 2299 | AA42: =urbanthreads_q4[[#This Row],[Net revenue]]/urbanthreads_q4[[#This Row],[Total]] -> 1 | AB42: =TEXT(urbanthreads_q4[[#This Row],[Order Date]],"mm-yyyy") -> 10-2024 | AC42: =YEAR(urbanthreads_q4[[#This Row],[Order Date]]) & "-W" & WEEKNUM(urbanthreads_q4[[#This Row],[Order Date]], 2) -> 2024-W41 | AD42: =IF(urbanthreads_q4[[#This Row],[Payment]]="COD","COD","Prepaid") -> Prepaid
A43: UT-100336 | B43: 45654 | C43: CUST_10335 | D43: New | E43: DRS-WLC-S | F43: Dresses | G43: Welcome 2025 Dress | H43: 4099 | I43: 1 | J43: 4099 | L43: 0 | M43: Credit Card | N43: Instagram Shop | O43: Chennai | P43: Tamil Nadu | Q43: Bangalore | R43: 45681 | S43: Delivered | T43: Yes | U43: Size Issue | V43: 45709 | W43: Processed | X43: =IF(urbanthreads_q4[[#This Row],[Qty]]>0,"Valid","Invalid") -> Valid | Y43: =urbanthreads_q4[[#This Row],[Total]]*urbanthreads_q4[[#This Row],[Disc %]]/100 -> 0 | Z43: =urbanthreads_q4[[#This Row],[Total]]-urbanthreads_q4[[#This Row],[Disc %]] -> 4099 | AA43: =urbanthreads_q4[[#This Row],[Net revenue]]/urbanthreads_q4[[#This Row],[Total]] -> 1 | AB43: =TEXT(urbanthreads_q4[[#This Row],[Order Date]],"mm-yyyy") -> 12-2024 | AC43: =YEAR(urbanthreads_q4[[#This Row],[Order Date]]) & "-W" & WEEKNUM(urbanthreads_q4[[#This Row],[Order Date]], 2) -> 2024-W52 | AD43: =IF(urbanthreads_q4[[#This Row],[Payment]]="COD","COD","Prepaid") -> Prepaid
A44: UT-100043 | B44: 45575 | C44: CUST_10042 | D44: New | E44: OUT-DNM-L | F44: Outerwear | G44: Denim Vest | H44: 2499 | I44: 1 | J44: 2499 | L44: 0 | M44: Wallet | N44: Website | O44: Chandigarh | P44: Punjab | Q44: Delhi | R44: 45585 | S44: Delivered | T44: No | W44: Not Applicable | X44: =IF(urbanthreads_q4[[#This Row],[Qty]]>0,"Valid","Invalid") -> Valid | Y44: =urbanthreads_q4[[#This Row],[Total]]*urbanthreads_q4[[#This Row],[Disc %]]/100 -> 0 | Z44: =urbanthreads_q4[[#This Row],[Total]]-urbanthreads_q4[[#This Row],[Disc %]] -> 2499 | AA44: =urbanthreads_q4[[#This Row],[Net revenue]]/urbanthreads_q4[[#This Row],[Total]] -> 1 | AB44: =TEXT(urbanthreads_q4[[#This Row],[Order Date]],"mm-yyyy") -> 10-2024 | AC44: =YEAR(urbanthreads_q4[[#This Row],[Order Date]]) & "-W" & WEEKNUM(urbanthreads_q4[[#This Row],[Order Date]], 2) -> 2024-W41 | AD44: =IF(urbanthreads_q4[[#This Row],[Payment]]="COD","COD","Prepaid") -> Prepaid
A45: UT-100338 | B45: 45655 | C45: CUST_10337 | D45: New | E45: OUT-HOP-L | F45: Outerwear | G45: Hope Coat | H45: 5799 | I45: 1 | J45: 5799 | L45: 0 | M45: COD | N45: Mobile App | O45: Pune | P45: Maharashtra | Q45: Mumbai | R45: 45682 | S45: Delivered | T45: Yes | U45: Changed Mind | V45: 45710 | W45: Processed | X45: =IF(urbanthreads_q4[[#This Row],[Qty]]>0,"Valid","Invalid") -> Valid | Y45: =urbanthreads_q4[[#This Row],[Total]]*urbanthreads_q4[[#This Row],[Disc %]]/100 -> 0 | Z45: =urbanthreads_q4[[#This Row],[Total]]-urbanthreads_q4[[#This Row],[Disc %]] -> 5799 | AA45: =urbanthreads_q4[[#This Row],[Net revenue]]/urbanthreads_q4[[#This Row],[Total]] -> 1 | AB45: =TEXT(urbanthreads_q4[[#This Row],[Order Date]],"mm-yyyy") -> 12-2024 | AC45: =YEAR(urbanthreads_q4[[#This Row],[Order Date]]) & "-W" & WEEKNUM(urbanthreads_q4[[#This Row],[Order Date]], 2) -> 2024-W52 | AD45: =IF(urbanthreads_q4[[#This Row],[Payment]]="COD","COD","Prepaid") -> COD
A46: UT-100045 | B46: 45576 | C46: CUST_10044 | D46: New | E46: BOT-CHP-M | F46: Bottoms | G46: Chino Pants | H46: 1999 | I46: 1 | J46: 1999 | K46: FIRST15 | L46: 15 | M46: UPI | N46: Mobile App | O46: Gurgaon | P46: Haryana | Q46: Delhi | R46: 45584 | S46: Delivered | T46: No | W46: Not Applicable | X46: =IF(urbanthreads_q4[[#This Row],[Qty]]>0,"Valid","Invalid") -> Valid | Y46: =urbanthreads_q4[[#This Row],[Total]]*urbanthreads_q4[[#This Row],[Disc %]]/100 -> 299.85 | Z46: =urbanthreads_q4[[#This Row],[Total]]-urbanthreads_q4[[#This Row],[Disc %]] -> 1984 | AA46: =urbanthreads_q4[[#This Row],[Net revenue]]/urbanthreads_q4[[#This Row],[Total]] -> 0.99249625 | AB46: =TEXT(urbanthreads_q4[[#This Row],[Order Date]],"mm-yyyy") -> 10-2024 | AC46: =YEAR(urbanthreads_q4[[#This Row],[Order Date]]) & "-W" & WEEKNUM(urbanthreads_q4[[#This Row],[Order Date]], 2) -> 2024-W41 | AD46: =IF(urbanthreads_q4[[#This Row],[Payment]]="COD","COD","Prepaid") -> Prepaid
A47: UT-100046 | B47: 45576 | C47: CUST_10045 | D47: Returning | E47: DRS-WRP-M | F47: Dresses | G47: Wrap Dress | H47: 2599 | I47: 1 | J47: 2599 | L47: 0 | M47: Credit Card | N47: Website | O47: Indore | P47: Madhya Pradesh | Q47: Mumbai | R47: 45585 | S47: Delivered | T47: No | W47: Not Applicable | X47: =IF(urbanthreads_q4[[#This Row],[Qty]]>0,"Valid","Invalid") -> Valid | Y47: =urbanthreads_q4[[#This Row],[Total]]*urbanthreads_q4[[#This Row],[Disc %]]/100 -> 0 | Z47: =urbanthreads_q4[[#This Row],[Total]]-urbanthreads_q4[[#This Row],[Disc %]] -> 2599 | AA47: =urbanthreads_q4[[#This Row],[Net revenue]]/urbanthreads_q4[[#This Row],[Total]] -> 1 | AB47: =TEXT(urbanthreads_q4[[#This Row],[Order Date]],"mm-yyyy") -> 10-2024 | AC47: =YEAR(urbanthreads_q4[[#This Row],[Order Date]]) & "-W" & WEEKNUM(urbanthreads_q4[[#This Row],[Order Date]], 2) -> 2024-W41 | AD47: =IF(urbanthreads_q4[[#This Row],[Payment]]="COD","COD","Prepaid") -> Prepaid
A48: UT-100047 | B48: 45576 | C48: CUST_10046 | D48: New | E48: TOP-STR-S | F48: Tops | G48: Striped Tee | H48: 1299 | I48: 1 | J48: 1299 | L48: 0 | M48: COD | N48: Instagram Shop | O48: Surat | P48: Gujarat | Q48: Mumbai | S48: RTO | T48: No | W48: Not Applicable | X48: =IF(urbanthreads_q4[[#This Row],[Qty]]>0,"Valid","Invalid") -> Valid | Y48: =urbanthreads_q4[[#This Row],[Total]]*urbanthreads_q4[[#This Row],[Disc %]]/100 -> 0 | Z48: =urbanthreads_q4[[#This Row],[Total]]-urbanthreads_q4[[#This Row],[Disc %]] -> 1299 | AA48: =urbanthreads_q4[[#This Row],[Net revenue]]/urbanthreads_q4[[#This Row],[Total]] -> 1 | AB48: =TEXT(urbanthreads_q4[[#This Row],[Order Date]],"mm-yyyy") -> 10-2024 | AC48: =YEAR(urbanthreads_q4[[#This Row],[Order Date]]) & "-W" & WEEKNUM(urbanthreads_q4[[#This Row],[Order Date]], 2) -> 2024-W41 | AD48: =IF(urbanthreads_q4[[#This Row],[Payment]]="COD","COD","Prepaid") -> COD
A49: UT-100339 | B49: 45655 | C49: CUST_10338 | D49: Returning | E49: ACC-DRM-OS | F49: Accessories | G49: Dream Catcher Earrings | H49: 699 | I49: 2 | J49: 1398 | L49: 0 | M49: Wallet | N49: Instagram Shop | O49: Ahmedabad | P49: Gujarat | Q49: Mumbai | R49: 45681 | S49: Delivered | T49: Yes | U49: Quality Defect | V49: 45708 | W49: Processed | X49: =IF(urbanthreads_q4[[#This Row],[Qty]]>0,"Valid","Invalid") -> Valid | Y49: =urbanthreads_q4[[#This Row],[Total]]*urbanthreads_q4[[#This Row],[Disc %]]/100 -> 0 | Z49: =urbanthreads_q4[[#This Row],[Total]]-urbanthreads_q4[[#This Row],[Disc %]] -> 1398 | AA49: =urbanthreads_q4[[#This Row],[Net revenue]]/urbanthreads_q4[[#This Row],[Total]] -> 1 | AB49: =TEXT(urbanthreads_q4[[#This Row],[Order Date]],"mm-yyyy") -> 12-2024 | AC49: =YEAR(urbanthreads_q4[[#This Row],[Order Date]]) & "-W" & WEEKNUM(urbanthreads_q4[[#This Row],[Order Date]], 2) -> 2024-W52 | AD49: =IF(urbanthreads_q4[[#This Row],[Payment]]="COD","COD","Prepaid") -> Prepaid
A50: UT-100049 | B50: 45577 | C50: CUST_10048 | D50: New | E50: ACC-EAR-OS | F50: Accessories | G50: Hoop Earrings | H50: 799 | I50: 2 | J50: 1598 | L50: 0 | M50: UPI | N50: Website | O50: Bhopal | P50: Madhya Pradesh | Q50: Mumbai | R50: 45585 | S50: Delivered | T50: No | W50: Not Applicable | X50: =IF(urbanthreads_q4[[#This Row],[Qty]]>0,"Valid","Invalid") -> Valid | Y50: =urbanthreads_q4[[#This Row],[Total]]*urbanthreads_q4[[#This Row],[Disc %]]/100 -> 0 | Z50: =urbanthreads_q4[[#This Row],[Total]]-urbanthreads_q4[[#This Row],[Disc %]] -> 1598 | AA50: =urbanthreads_q4[[#This Row],[Net revenue]]/urbanthreads_q4[[#This Row],[Total]] -> 1 | AB50: =TEXT(urbanthreads_q4[[#This Row],[Order Date]],"mm-yyyy") -> 10-2024 | AC50: =YEAR(urbanthreads_q4[[#This Row],[Order Date]]) & "-W" & WEEKNUM(urbanthreads_q4[[#This Row],[Order Date]], 2) -> 2024-W41 | AD50: =IF(urbanthreads_q4[[#This Row],[Payment]]="COD","COD","Prepaid") -> Prepaid
A51: UT-100050 | B51: 45577 | C51: CUST_10049 | D51: Returning | E51: BOT-LGN-S | F51: Bottoms | G51: Leggings | H51: 999 | I51: 2 | J51: 1998 | L51: 0 | M51: Wallet | N51: Mobile App | O51: Nagpur | P51: Maharashtra | Q51: Mumbai | R51: 45584 | S51: Delivered | T51: No | W51: Not Applicable | X51: =IF(urbanthreads_q4[[#This Row],[Qty]]>0,"Valid","Invalid") -> Valid | Y51: =urbanthreads_q4[[#This Row],[Total]]*urbanthreads_q4[[#This Row],[Disc %]]/100 -> 0 | Z51: =urbanthreads_q4[[#This Row],[Total]]-urbanthreads_q4[[#This Row],[Disc %]] -> 1998 | AA51: =urbanthreads_q4[[#This Row],[Net revenue]]/urbanthreads_q4[[#This Row],[Total]] -> 1 | AB51: =TEXT(urbanthreads_q4[[#This Row],[Order Date]],"mm-yyyy") -> 10-2024 | AC51: =YEAR(urbanthreads_q4[[#This Row],[Order Date]]) & "-W" & WEEKNUM(urbanthreads_q4[[#This Row],[Order Date]], 2) -> 2024-W41 | AD51: =IF(urbanthreads_q4[[#This Row],[Payment]]="COD","COD","Prepaid") -> Prepaid
A52: UT-100341 | B52: 45655 | C52: CUST_10340 | D52: New | E52: DRS-PRO-L | F52: Dresses | G52: Promise Dress | H52: 3899 | I52: 1 | J52: 3899 | L52: 0 | M52: Credit Card | N52: Mobile App | O52: Lucknow | P52: Uttar Pradesh | Q52: Delhi | R52: 45683 | S52: Delivered | T52: Yes | U52: Size Issue | V52: 45711 | W52: Processed | X52: =IF(urbanthreads_q4[[#This Row],[Qty]]>0,"Valid","Invalid") -> Valid | Y52: =urbanthreads_q4[[#This Row],[Total]]*urbanthreads_q4[[#This Row],[Disc %]]/100 -> 0 | Z52: =urbanthreads_q4[[#This Row],[Total]]-urbanthreads_q4[[#This Row],[Disc %]] -> 3899 | AA52: =urbanthreads_q4[[#This Row],[Net revenue]]/urbanthreads_q4[[#This Row],[Total]] -> 1 | AB52: =TEXT(urbanthreads_q4[[#This Row],[Order Date]],"mm-yyyy") -> 12-2024 | AC52: =YEAR(urbanthreads_q4[[#This Row],[Order Date]]) & "-W" & WEEKNUM(urbanthreads_q4[[#This Row],[Order Date]], 2) -> 2024-W52 | AD52: =IF(urbanthreads_q4[[#This Row],[Payment]]="COD","COD","Prepaid") -> Prepaid
A53: UT-100052 | B53: 45578 | C53: CUST_10051 | D53: New | E53: TOP-LCE-M | F53: Tops | G53: Lace Top | H53: 1699 | I53: 1 | J53: 1699 | K53: FLAT10 | L53: 10 | M53: Credit Card | N53: Website | O53: Kochi | P53: Kerala | Q53: Bangalore | R53: 45586 | S53: Delivered | T53: No | W53: Not Applicable | X53: =IF(urbanthreads_q4[[#This Row],[Qty]]>0,"Valid","Invalid") -> Valid | Y53: =urbanthreads_q4[[#This Row],[Total]]*urbanthreads_q4[[#This Row],[Disc %]]/100 -> 169.9 | Z53: =urbanthreads_q4[[#This Row],[Total]]-urbanthreads_q4[[#This Row],[Disc %]] -> 1689 | AA53: =urbanthreads_q4[[#This Row],[Net revenue]]/urbanthreads_q4[[#This Row],[Total]] -> 0.99411418 | AB53: =TEXT(urbanthreads_q4[[#This Row],[Order Date]],"mm-yyyy") -> 10-2024 | AC53: =YEAR(urbanthreads_q4[[#This Row],[Order Date]]) & "-W" & WEEKNUM(urbanthreads_q4[[#This Row],[Order Date]], 2) -> 2024-W41 | AD53: =IF(urbanthreads_q4[[#This Row],[Payment]]="COD","COD","Prepaid") -> Prepaid
A54: UT-100286 | B54: 45642 | C54: CUST_10285 | D54: New | E54: DRS-BLS-M | F54: Dresses | G54: Bliss Dress | H54: 3899 | I54: 1 | J54: 3899 | K54: Dec20 | L54: 20 | M54: Credit Card | N54: Website | O54: Bangalore | P54: Karnataka | Q54: Bangalore | R54: 45661 | S54: Delivered | T54: Yes | U54: Size Issue | V54: 45689 | W54: Processed | X54: =IF(urbanthreads_q4[[#This Row],[Qty]]>0,"Valid","Invalid") -> Valid | Y54: =urbanthreads_q4[[#This Row],[Total]]*urbanthreads_q4[[#This Row],[Disc %]]/100 -> 779.8 | Z54: =urbanthreads_q4[[#This Row],[Total]]-urbanthreads_q4[[#This Row],[Disc %]] -> 3879 | AA54: =urbanthreads_q4[[#This Row],[Net revenue]]/urbanthreads_q4[[#This Row],[Total]] -> 0.99487048 | AB54: =TEXT(urbanthreads_q4[[#This Row],[Order Date]],"mm-yyyy") -> 12-2024 | AC54: =YEAR(urbanthreads_q4[[#This Row],[Order Date]]) & "-W" & WEEKNUM(urbanthreads_q4[[#This Row],[Order Date]], 2) -> 2024-W51 | AD54: =IF(urbanthreads_q4[[#This Row],[Payment]]="COD","COD","Prepaid") -> Prepaid
A55: UT-100054 | B55: 45578 | C55: CUST_10053 | D55: Returning | E55: ACC-NCK-OS | F55: Accessories | G55: Pendant Necklace | H55: 1299 | I55: 1 | J55: 1299 | L55: 0 | M55: COD | N55: Instagram Shop | O55: Thiruvananthapuram | P55: Kerala | Q55: Bangalore | R55: 45587 | S55: Delivered | T55: No | W55: Not Applicable | X55: =IF(urbanthreads_q4[[#This Row],[Qty]]>0,"Valid","Invalid") -> Valid | Y55: =urbanthreads_q4[[#This Row],[Total]]*urbanthreads_q4[[#This Row],[Disc %]]/100 -> 0 | Z55: =urbanthreads_q4[[#This Row],[Total]]-urbanthreads_q4[[#This Row],[Disc %]] -> 1299 | AA55: =urbanthreads_q4[[#This Row],[Net revenue]]/urbanthreads_q4[[#This Row],[Total]] -> 1 | AB55: =TEXT(urbanthreads_q4[[#This Row],[Order Date]],"mm-yyyy") -> 10-2024 | AC55: =YEAR(urbanthreads_q4[[#This Row],[Order Date]]) & "-W" & WEEKNUM(urbanthreads_q4[[#This Row],[Order Date]], 2) -> 2024-W41 | AD55: =IF(urbanthreads_q4[[#This Row],[Payment]]="COD","COD","Prepaid") -> COD
A56: UT-100055 | B56: 45578 | C56: CUST_10054 | D56: New | E56: BOT-WID-M | F56: Bottoms | G56: Wide Leg Pants | H56: 2099 | I56: 1 | J56: 2099 | K56: DIWALI20 | L56: 20 | M56: Credit Card | N56: Website | O56: Mysore | P56: Karnataka | Q56: Bangalore | R56: 45589 | S56: Delivered | T56: No | W56: Not Applicable | X56: =IF(urbanthreads_q4[[#This Row],[Qty]]>0,"Valid","Invalid") -> Valid | Y56: =urbanthreads_q4[[#This Row],[Total]]*urbanthreads_q4[[#This Row],[Disc %]]/100 -> 419.8 | Z56: =urbanthreads_q4[[#This Row],[Total]]-urbanthreads_q4[[#This Row],[Disc %]] -> 2079 | AA56: =urbanthreads_q4[[#This Row],[Net revenue]]/urbanthreads_q4[[#This Row],[Total]] -> 0.99047165 | AB56: =TEXT(urbanthreads_q4[[#This Row],[Order Date]],"mm-yyyy") -> 10-2024 | AC56: =YEAR(urbanthreads_q4[[#This Row],[Order Date]]) & "-W" & WEEKNUM(urbanthreads_q4[[#This Row],[Order Date]], 2) -> 2024-W41 | AD56: =IF(urbanthreads_q4[[#This Row],[Payment]]="COD","COD","Prepaid") -> Prepaid
A57: UT-100288 | B57: 45642 | C57: CUST_10287 | D57: New | E57: OUT-CLB-M | F57: Outerwear | G57: Celebration Blazer | H57: 5299 | I57: 1 | J57: 5299 | L57: 0 | M57: COD | N57: Instagram Shop | O57: Delhi | P57: Delhi | Q57: Delhi | R57: 45662 | S57: Delivered | T57: Yes | U57: Changed Mind | V57: 45690 | W57: Processed | X57: =IF(urbanthreads_q4[[#This Row],[Qty]]>0,"Valid","Invalid") -> Valid | Y57: =urbanthreads_q4[[#This Row],[Total]]*urbanthreads_q4[[#This Row],[Disc %]]/100 -> 0 | Z57: =urbanthreads_q4[[#This Row],[Total]]-urbanthreads_q4[[#This Row],[Disc %]] -> 5299 | AA57: =urbanthreads_q4[[#This Row],[Net revenue]]/urbanthreads_q4[[#This Row],[Total]] -> 1 | AB57: =TEXT(urbanthreads_q4[[#This Row],[Order Date]],"mm-yyyy") -> 12-2024 | AC57: =YEAR(urbanthreads_q4[[#This Row],[Order Date]]) & "-W" & WEEKNUM(urbanthreads_q4[[#This Row],[Order Date]], 2) -> 2024-W51 | AD57: =IF(urbanthreads_q4[[#This Row],[Payment]]="COD","COD","Prepaid") -> COD
A58: UT-100057 | B58: 45579 | C58: CUST_10056 | D58: New | E58: TOP-PEP-M | F58: Tops | G58: Peplum Top | H58: 1499 | I58: 1 | J58: 1499 | L58: 0 | M58: Wallet | N58: Website | O58: Rajkot | P58: Gujarat | Q58: Mumbai | R58: 45587 | S58: Delivered | T58: No | W58: Not Applicable | X58: =IF(urbanthreads_q4[[#This Row],[Qty]]>0,"Valid","Invalid") -> Valid | Y58: =urbanthreads_q4[[#This Row],[Total]]*urbanthreads_q4[[#This Row],[Disc %]]/100 -> 0 | Z58: =urbanthreads_q4[[#This Row],[Total]]-urbanthreads_q4[[#This Row],[Disc %]] -> 1499 | AA58: =urbanthreads_q4[[#This Row],[Net revenue]]/urbanthreads_q4[[#This Row],[Total]] -> 1 | AB58: =TEXT(urbanthreads_q4[[#This Row],[Order Date]],"mm-yyyy") -> 10-2024 | AC58: =YEAR(urbanthreads_q4[[#This Row],[Order Date]]) & "-W" & WEEKNUM(urbanthreads_q4[[#This Row],[Order Date]], 2) -> 2024-W42 | AD58: =IF(urbanthreads_q4[[#This Row],[Payment]]="COD","COD","Prepaid") -> Prepaid
A59: UT-100290 | B59: 45643 | C59: CUST_10289 | D59: New | E59: TOP-PRY-M | F59: Tops | G59: Party Essential Top | H59: 1799 | I59: 1 | J59: 1799 | L59: 0 | M59: Debit Card | N59: Mobile App | O59: Noida | P59: Uttar Pradesh | Q59: Delhi | R59: 45662 | S59: Delivered | T59: Yes | U59: Quality Defect | V59: 45689 | W59: Processed | X59: =IF(urbanthreads_q4[[#This Row],[Qty]]>0,"Valid","Invalid") -> Valid | Y59: =urbanthreads_q4[[#This Row],[Total]]*urbanthreads_q4[[#This Row],[Disc %]]/100 -> 0 | Z59: =urbanthreads_q4[[#This Row],[Total]]-urbanthreads_q4[[#This Row],[Disc %]] -> 1799 | AA59: =urbanthreads_q4[[#This Row],[Net revenue]]/urbanthreads_q4[[#This Row],[Total]] -> 1 | AB59: =TEXT(urbanthreads_q4[[#This Row],[Order Date]],"mm-yyyy") -> 12-2024 | AC59: =YEAR(urbanthreads_q4[[#This Row],[Order Date]]) & "-W" & WEEKNUM(urbanthreads_q4[[#This Row],[Order Date]], 2) -> 2024-W51 | AD59: =IF(urbanthreads_q4[[#This Row],[Payment]]="COD","COD","Prepaid") -> Prepaid
A60: UT-100059 | B60: 45579 | C60: CUST_10058 | D60: New | E60: ACC-BRC-OS | F60: Accessories | G60: Charm Bracelet | H60: 899 | I60: 1 | J60: 899 | L60: 0 | M60: Credit Card | N60: Mobile App | O60: Mumbai | P60: Maharashtra | Q60: Mumbai | R60: 45588 | S60: Delivered | T60: No | W60: Not Applicable | X60: =IF(urbanthreads_q4[[#This Row],[Qty]]>0,"Valid","Invalid") -> Valid | Y60: =urbanthreads_q4[[#This Row],[Total]]*urbanthreads_q4[[#This Row],[Disc %]]/100 -> 0 | Z60: =urbanthreads_q4[[#This Row],[Total]]-urbanthreads_q4[[#This Row],[Disc %]] -> 899 | AA60: =urbanthreads_q4[[#This Row],[Net revenue]]/urbanthreads_q4[[#This Row],[Total]] -> 1 | AB60: =TEXT(urbanthreads_q4[[#This Row],[Order Date]],"mm-yyyy") -> 10-2024 | AC60: =YEAR(urbanthreads_q4[[#This Row],[Order Date]]) & "-W" & WEEKNUM(urbanthreads_q4[[#This Row],[Order Date]], 2) -> 2024-W42 | AD60: =IF(urbanthreads_q4[[#This Row],[Payment]]="COD","COD","Prepaid") -> Prepaid
A61: UT-100060 | B61: 45580 | C61: CUST_10059 | D61: New | E61: BOT-CRP-S | F61: Bottoms | G61: Cropped Pants | H61: 1799 | I61: 1 | J61: 1799 | L61: 0 | M61: COD | N61: Website | O61: Delhi | P61: Delhi | Q61: Delhi | S61: RTO | T61: No | W61: Not Applicable | X61: =IF(urbanthreads_q4[[#This Row],[Qty]]>0,"Valid","Invalid") -> Valid | Y61: =urbanthreads_q4[[#This Row],[Total]]*urbanthreads_q4[[#This Row],[Disc %]]/100 -> 0 | Z61: =urbanthreads_q4[[#This Row],[Total]]-urbanthreads_q4[[#This Row],[Disc %]] -> 1799 | AA61: =urbanthreads_q4[[#This Row],[Net revenue]]/urbanthreads_q4[[#This Row],[Total]] -> 1 | AB61: =TEXT(urbanthreads_q4[[#This Row],[Order Date]],"mm-yyyy") -> 10-2024 | AC61: =YEAR(urbanthreads_q4[[#This Row],[Order Date]]) & "-W" & WEEKNUM(urbanthreads_q4[[#This Row],[Order Date]], 2) -> 2024-W42 | AD61: =IF(urbanthreads_q4[[#This Row],[Payment]]="COD","COD","Prepaid") -> COD
A62: UT-100291 | B62: 45643 | C62: CUST_10290 | D62: New | E62: DRS-SHN-L | F62: Dresses | G62: Shine On Dress | H62: 4199 | I62: 1 | J62: 4199 | L62: 0 | M62: Credit Card | N62: Instagram Shop | O62: Gurgaon | P62: Haryana | Q62: Delhi | R62: 45663 | S62: Delivered | T62: Yes | U62: Size Issue | V62: 45691 | W62: Processed | X62: =IF(urbanthreads_q4[[#This Row],[Qty]]>0,"Valid","Invalid") -> Valid | Y62: =urbanthreads_q4[[#This Row],[Total]]*urbanthreads_q4[[#This Row],[Disc %]]/100 -> 0 | Z62: =urbanthreads_q4[[#This Row],[Total]]-urbanthreads_q4[[#This Row],[Disc %]] -> 4199 | AA62: =urbanthreads_q4[[#This Row],[Net revenue]]/urbanthreads_q4[[#This Row],[Total]] -> 1 | AB62: =TEXT(urbanthreads_q4[[#This Row],[Order Date]],"mm-yyyy") -> 12-2024 | AC62: =YEAR(urbanthreads_q4[[#This Row],[Order Date]]) & "-W" & WEEKNUM(urbanthreads_q4[[#This Row],[Order Date]], 2) -> 2024-W51 | AD62: =IF(urbanthreads_q4[[#This Row],[Payment]]="COD","COD","Prepaid") -> Prepaid
A63: UT-100062 | B63: 45580 | C63: CUST_10061 | D63: Returning | E63: TOP-HLT-L | F63: Tops | G63: Halter Top | H63: 1399 | I63: 1 | J63: 1399 | L63: 0 | M63: UPI | N63: Mobile App | O63: Chennai | P63: Tamil Nadu | Q63: Bangalore | R63: 45589 | S63: Delivered | T63: No | W63: Not Applicable | X63: =IF(urbanthreads_q4[[#This Row],[Qty]]>0,"Valid","Invalid") -> Valid | Y63: =urbanthreads_q4[[#This Row],[Total]]*urbanthreads_q4[[#This Row],[Disc %]]/100 -> 0 | Z63: =urbanthreads_q4[[#This Row],[Total]]-urbanthreads_q4[[#This Row],[Disc %]] -> 1399 | AA63: =urbanthreads_q4[[#This Row],[Net revenue]]/urbanthreads_q4[[#This Row],[Total]] -> 1 | AB63: =TEXT(urbanthreads_q4[[#This Row],[Order Date]],"mm-yyyy") -> 10-2024 | AC63: =YEAR(urbanthreads_q4[[#This Row],[Order Date]]) & "-W" & WEEKNUM(urbanthreads_q4[[#This Row],[Order Date]], 2) -> 2024-W42 | AD63: =IF(urbanthreads_q4[[#This Row],[Payment]]="COD","COD","Prepaid") -> Prepaid
A64: UT-100293 | B64: 45643 | C64: CUST_10292 | D64: New | E64: OUT-DZL-M | F64: Outerwear | G64: Dazzle Jacket | H64: 5499 | I64: 1 | J64: 5499 | L64: 0 | M64: COD | N64: Mobile App | O64: Surat | P64: Gujarat | Q64: Mumbai | R64: 45664 | S64: Delivered | T64: Yes | U64: Wrong Item | V64: 45692 | W64: Processed | X64: =IF(urbanthreads_q4[[#This Row],[Qty]]>0,"Valid","Invalid") -> Valid | Y64: =urbanthreads_q4[[#This Row],[Total]]*urbanthreads_q4[[#This Row],[Disc %]]/100 -> 0 | Z64: =urbanthreads_q4[[#This Row],[Total]]-urbanthreads_q4[[#This Row],[Disc %]] -> 5499 | AA64: =urbanthreads_q4[[#This Row],[Net revenue]]/urbanthreads_q4[[#This Row],[Total]] -> 1 | AB64: =TEXT(urbanthreads_q4[[#This Row],[Order Date]],"mm-yyyy") -> 12-2024 | AC64: =YEAR(urbanthreads_q4[[#This Row],[Order Date]]) & "-W" & WEEKNUM(urbanthreads_q4[[#This Row],[Order Date]], 2) -> 2024-W51 | AD64: =IF(urbanthreads_q4[[#This Row],[Payment]]="COD","COD","Prepaid") -> COD
A65: UT-100064 | B65: 45581 | C65: CUST_10063 | D65: New | E65: ACC-RNG-OS | F65: Accessories | G65: Cocktail Ring | H65: 699 | I65: 2 | J65: 1398 | K65: FLAT10 | L65: 10 | M65: Wallet | N65: Instagram Shop | O65: Pune | P65: Maharashtra | Q65: Mumbai | R65: 45590 | S65: Delivered | T65: No | W65: Not Applicable | X65: =IF(urbanthreads_q4[[#This Row],[Qty]]>0,"Valid","Invalid") -> Valid | Y65: =urbanthreads_q4[[#This Row],[Total]]*urbanthreads_q4[[#This Row],[Disc %]]/100 -> 139.8 | Z65: =urbanthreads_q4[[#This Row],[Total]]-urbanthreads_q4[[#This Row],[Disc %]] -> 1388 | AA65: =urbanthreads_q4[[#This Row],[Net revenue]]/urbanthreads_q4[[#This Row],[Total]] -> 0.99284692 | AB65: =TEXT(urbanthreads_q4[[#This Row],[Order Date]],"mm-yyyy") -> 10-2024 | AC65: =YEAR(urbanthreads_q4[[#This Row],[Order Date]]) & "-W" & WEEKNUM(urbanthreads_q4[[#This Row],[Order Date]], 2) -> 2024-W42 | AD65: =IF(urbanthreads_q4[[#This Row],[Payment]]="COD","COD","Prepaid") -> Prepaid
A66: UT-100295 | B66: 45644 | C66: CUST_10294 | D66: New | E66: TOP-SLB-L | F66: Tops | G66: Celebrate Top | H66: 2299 | I66: 1 | J66: 2299 | K66: Dec20 | L66: 20 | M66: Debit Card | N66: Website | O66: Bhopal | P66: Madhya Pradesh | Q66: Mumbai | R66: 45664 | S66: Delivered | T66: Yes | U66: Damaged in Transit | V66: 45691 | W66: Processed | X66: =IF(urbanthreads_q4[[#This Row],[Qty]]>0,"Valid","Invalid") -> Valid | Y66: =urbanthreads_q4[[#This Row],[Total]]*urbanthreads_q4[[#This Row],[Disc %]]/100 -> 459.8 | Z66: =urbanthreads_q4[[#This Row],[Total]]-urbanthreads_q4[[#This Row],[Disc %]] -> 2279 | AA66: =urbanthreads_q4[[#This Row],[Net revenue]]/urbanthreads_q4[[#This Row],[Total]] -> 0.99130057 | AB66: =TEXT(urbanthreads_q4[[#This Row],[Order Date]],"mm-yyyy") -> 12-2024 | AC66: =YEAR(urbanthreads_q4[[#This Row],[Order Date]]) & "-W" & WEEKNUM(urbanthreads_q4[[#This Row],[Order Date]], 2) -> 2024-W51 | AD66: =IF(urbanthreads_q4[[#This Row],[Payment]]="COD","COD","Prepaid") -> Prepaid
A67: UT-100066 | B67: 45581 | C67: CUST_10065 | D67: Returning | E67: DRS-KNT-S | F67: Dresses | G67: Knit Dress | H67: 2499 | I67: 1 | J67: 2499 | L67: 0 | M67: Credit Card | N67: Website | O67: Jaipur | P67: Rajasthan | Q67: Delhi | R67: 45591 | S67: Delivered | T67: No | W67: Not Applicable | X67: =IF(urbanthreads_q4[[#This Row],[Qty]]>0,"Valid","Invalid") -> Valid | Y67: =urbanthreads_q4[[#This Row],[Total]]*urbanthreads_q4[[#This Row],[Disc %]]/100 -> 0 | Z67: =urbanthreads_q4[[#This Row],[Total]]-urbanthreads_q4[[#This Row],[Disc %]] -> 2499 | AA67: =urbanthreads_q4[[#This Row],[Net revenue]]/urbanthreads_q4[[#This Row],[Total]] -> 1 | AB67: =TEXT(urbanthreads_q4[[#This Row],[Order Date]],"mm-yyyy") -> 10-2024 | AC67: =YEAR(urbanthreads_q4[[#This Row],[Order Date]]) & "-W" & WEEKNUM(urbanthreads_q4[[#This Row],[Order Date]], 2) -> 2024-W42 | AD67: =IF(urbanthreads_q4[[#This Row],[Payment]]="COD","COD","Prepaid") -> Prepaid
A68: UT-100297 | B68: 45644 | C68: CUST_10296 | D68: New | E68: BOT-BRT-M | F68: Bottoms | G68: Bright Night Pants | H68: 2499 | I68: 1 | J68: 2499 | L68: 0 | M68: UPI | N68: Instagram Shop | O68: Coimbatore | P68: Tamil Nadu | Q68: Bangalore | R68: 45665 | S68: Delivered | T68: Yes | U68: Size Issue | V68: 45693 | W68: Processed | X68: =IF(urbanthreads_q4[[#This Row],[Qty]]>0,"Valid","Invalid") -> Valid | Y68: =urbanthreads_q4[[#This Row],[Total]]*urbanthreads_q4[[#This Row],[Disc %]]/100 -> 0 | Z68: =urbanthreads_q4[[#This Row],[Total]]-urbanthreads_q4[[#This Row],[Disc %]] -> 2499 | AA68: =urbanthreads_q4[[#This Row],[Net revenue]]/urbanthreads_q4[[#This Row],[Total]] -> 1 | AB68: =TEXT(urbanthreads_q4[[#This Row],[Order Date]],"mm-yyyy") -> 12-2024 | AC68: =YEAR(urbanthreads_q4[[#This Row],[Order Date]]) & "-W" & WEEKNUM(urbanthreads_q4[[#This Row],[Order Date]], 2) -> 2024-W51 | AD68: =IF(urbanthreads_q4[[#This Row],[Payment]]="COD","COD","Prepaid") -> Prepaid
A69: UT-100068 | B69: 45582 | C69: CUST_10067 | D69: New | E69: OUT-SHR-L | F69: Outerwear | G69: Shrug | H69: 1299 | I69: 1 | J69: 1299 | L69: 0 | M69: Debit Card | N69: Mobile App | O69: Bangalore | P69: Karnataka | Q69: Bangalore | R69: 45593 | S69: Delivered | T69: No | W69: Not Applicable | X69: =IF(urbanthreads_q4[[#This Row],[Qty]]>0,"Valid","Invalid") -> Valid | Y69: =urbanthreads_q4[[#This Row],[Total]]*urbanthreads_q4[[#This Row],[Disc %]]/100 -> 0 | Z69: =urbanthreads_q4[[#This Row],[Total]]-urbanthreads_q4[[#This Row],[Disc %]] -> 1299 | AA69: =urbanthreads_q4[[#This Row],[Net revenue]]/urbanthreads_q4[[#This Row],[Total]] -> 1 | AB69: =TEXT(urbanthreads_q4[[#This Row],[Order Date]],"mm-yyyy") -> 10-2024 | AC69: =YEAR(urbanthreads_q4[[#This Row],[Order Date]]) & "-W" & WEEKNUM(urbanthreads_q4[[#This Row],[Order Date]], 2) -> 2024-W42 | AD69: =IF(urbanthreads_q4[[#This Row],[Payment]]="COD","COD","Prepaid") -> Prepaid
A70: UT-100298 | B70: 45645 | C70: CUST_10297 | D70: New | E70: OUT-END-L | F70: Outerwear | G70: End of Year Coat | H70: 6799 | I70: 1 | J70: 6799 | K70: Dec20 | L70: 20 | M70: COD | N70: Website | O70: Kochi | P70: Kerala | Q70: Bangalore | R70: 45666 | S70: Delivered | T70: Yes | U70: Changed Mind | V70: 45694 | W70: Processed | X70: =IF(urbanthreads_q4[[#This Row],[Qty]]>0,"Valid","Invalid") -> Valid | Y70: =urbanthreads_q4[[#This Row],[Total]]*urbanthreads_q4[[#This Row],[Disc %]]/100 -> 1359.8 | Z70: =urbanthreads_q4[[#This Row],[Total]]-urbanthreads_q4[[#This Row],[Disc %]] -> 6779 | AA70: =urbanthreads_q4[[#This Row],[Net revenue]]/urbanthreads_q4[[#This Row],[Total]] -> 0.99705839 | AB70: =TEXT(urbanthreads_q4[[#This Row],[Order Date]],"mm-yyyy") -> 12-2024 | AC70: =YEAR(urbanthreads_q4[[#This Row],[Order Date]]) & "-W" & WEEKNUM(urbanthreads_q4[[#This Row],[Order Date]], 2) -> 2024-W51 | AD70: =IF(urbanthreads_q4[[#This Row],[Payment]]="COD","COD","Prepaid") -> COD
A71: UT-100070 | B71: 45582 | C71: CUST_10069 | D71: Returning | E71: BOT-FLR-S | F71: Bottoms | G71: Flared Jeans | H71: 2099 | I71: 1 | J71: 2099 | K71: FIRST15 | L71: 15 | M71: UPI | N71: Instagram Shop | O71: Delhi | P71: Delhi | Q71: Delhi | R71: 45594 | S71: Delivered | T71: No | W71: Not Applicable | X71: =IF(urbanthreads_q4[[#This Row],[Qty]]>0,"Valid","Invalid") -> Valid | Y71: =urbanthreads_q4[[#This Row],[Total]]*urbanthreads_q4[[#This Row],[Disc %]]/100 -> 314.85 | Z71: =urbanthreads_q4[[#This Row],[Total]]-urbanthreads_q4[[#This Row],[Disc %]] -> 2084 | AA71: =urbanthreads_q4[[#This Row],[Net revenue]]/urbanthreads_q4[[#This Row],[Total]] -> 0.99285374 | AB71: =TEXT(urbanthreads_q4[[#This Row],[Order Date]],"mm-yyyy") -> 10-2024 | AC71: =YEAR(urbanthreads_q4[[#This Row],[Order Date]]) & "-W" & WEEKNUM(urbanthreads_q4[[#This Row],[Order Date]], 2) -> 2024-W42 | AD71: =IF(urbanthreads_q4[[#This Row],[Payment]]="COD","COD","Prepaid") -> Prepaid
A72: UT-100071 | B72: 45582 | C72: CUST_10070 | D72: New | E72: DRS-PIN-M | F72: Dresses | G72: Pinafore Dress | H72: 2299 | I72: 1 | J72: 2299 | L72: 0 | M72: COD | N72: Mobile App | O72: Chandigarh | P72: Punjab | Q72: Delhi | S72: RTO | T72: No | W72: Not Applicable | X72: =IF(urbanthreads_q4[[#This Row],[Qty]]>0,"Valid","Invalid") -> Valid | Y72: =urbanthreads_q4[[#This Row],[Total]]*urbanthreads_q4[[#This Row],[Disc %]]/100 -> 0 | Z72: =urbanthreads_q4[[#This Row],[Total]]-urbanthreads_q4[[#This Row],[Disc %]] -> 2299 | AA72: =urbanthreads_q4[[#This Row],[Net revenue]]/urbanthreads_q4[[#This Row],[Total]] -> 1 | AB72: =TEXT(urbanthreads_q4[[#This Row],[Order Date]],"mm-yyyy") -> 10-2024 | AC72: =YEAR(urbanthreads_q4[[#This Row],[Order Date]]) & "-W" & WEEKNUM(urbanthreads_q4[[#This Row],[Order Date]], 2) -> 2024-W42 | AD72: =IF(urbanthreads_q4[[#This Row],[Payment]]="COD","COD","Prepaid") -> COD
A73: UT-100072 | B73: 45583 | C73: CUST_10071 | D73: New | E73: TOP-CRW-L | F73: Tops | G73: Crew Neck Tee | H73: 1199 | I73: 2 | J73: 2398 | L73: 0 | M73: Wallet | N73: Website | O73: Noida | P73: Uttar Pradesh | Q73: Delhi | R73: 45593 | S73: Delivered | T73: No | W73: Not Applicable | X73: =IF(urbanthreads_q4[[#This Row],[Qty]]>0,"Valid","Invalid") -> Valid | Y73: =urbanthreads_q4[[#This Row],[Total]]*urbanthreads_q4[[#This Row],[Disc %]]/100 -> 0 | Z73: =urbanthreads_q4[[#This Row],[Total]]-urbanthreads_q4[[#This Row],[Disc %]] -> 2398 | AA73: =urbanthreads_q4[[#This Row],[Net revenue]]/urbanthreads_q4[[#This Row],[Total]] -> 1 | AB73: =TEXT(urbanthreads_q4[[#This Row],[Order Date]],"mm-yyyy") -> 10-2024 | AC73: =YEAR(urbanthreads_q4[[#This Row],[Order Date]]) & "-W" & WEEKNUM(urbanthreads_q4[[#This Row],[Order Date]], 2) -> 2024-W42 | AD73: =IF(urbanthreads_q4[[#This Row],[Payment]]="COD","COD","Prepaid") -> Prepaid
A74: UT-100300 | B74: 45645 | C74: CUST_10299 | D74: New | E74: TOP-JOY-M | F74: Tops | G74: Joyful Top | H74: 1899 | I74: 1 | J74: 1899 | L74: 0 | M74: Debit Card | N74: Instagram Shop | O74: Thiruvananthapuram | P74: Kerala | Q74: Bangalore | R74: 45666 | S74: Delivered | T74: Yes | U74: Quality Defect | V74: 45693 | W74: Processed | X74: =IF(urbanthreads_q4[[#This Row],[Qty]]>0,"Valid","Invalid") -> Valid | Y74: =urbanthreads_q4[[#This Row],[Total]]*urbanthreads_q4[[#This Row],[Disc %]]/100 -> 0 | Z74: =urbanthreads_q4[[#This Row],[Total]]-urbanthreads_q4[[#This Row],[Disc %]] -> 1899 | AA74: =urbanthreads_q4[[#This Row],[Net revenue]]/urbanthreads_q4[[#This Row],[Total]] -> 1 | AB74: =TEXT(urbanthreads_q4[[#This Row],[Order Date]],"mm-yyyy") -> 12-2024 | AC74: =YEAR(urbanthreads_q4[[#This Row],[Order Date]]) & "-W" & WEEKNUM(urbanthreads_q4[[#This Row],[Order Date]], 2) -> 2024-W51 | AD74: =IF(urbanthreads_q4[[#This Row],[Payment]]="COD","COD","Prepaid") -> Prepaid
A75: UT-100074 | B75: 45583 | C75: CUST_10073 | D75: Returning | E75: ACC-SCR-OS | F75: Accessories | G75: Hair Scrunchie | H75: 299 | I75: 5 | J75: 1495 | L75: 0 | M75: UPI | N75: Mobile App | O75: Indore | P75: Madhya Pradesh | Q75: Mumbai | R75: 45592 | S75: Delivered | T75: No | W75: Not Applicable | X75: =IF(urbanthreads_q4[[#This Row],[Qty]]>0,"Valid","Invalid") -> Valid | Y75: =urbanthreads_q4[[#This Row],[Total]]*urbanthreads_q4[[#This Row],[Disc %]]/100 -> 0 | Z75: =urbanthreads_q4[[#This Row],[Total]]-urbanthreads_q4[[#This Row],[Disc %]] -> 1495 | AA75: =urbanthreads_q4[[#This Row],[Net revenue]]/urbanthreads_q4[[#This Row],[Total]] -> 1 | AB75: =TEXT(urbanthreads_q4[[#This Row],[Order Date]],"mm-yyyy") -> 10-2024 | AC75: =YEAR(urbanthreads_q4[[#This Row],[Order Date]]) & "-W" & WEEKNUM(urbanthreads_q4[[#This Row],[Order Date]], 2) -> 2024-W42 | AD75: =IF(urbanthreads_q4[[#This Row],[Payment]]="COD","COD","Prepaid") -> Prepaid
A76: UT-100301 | B76: 45645 | C76: CUST_10300 | D76: New | E76: DRS-WND-L | F76: Dresses | G76: Winter Wonder Dress | H76: 4499 | I76: 1 | J76: 4499 | K76: Dec20 | L76: 20 | M76: Credit Card | N76: Website | O76: Mysore | P76: Karnataka | Q76: Bangalore | R76: 45667 | S76: Delivered | T76: Yes | U76: Size Issue | V76: 45695 | W76: Processed | X76: =IF(urbanthreads_q4[[#This Row],[Qty]]>0,"Valid","Invalid") -> Valid | Y76: =urbanthreads_q4[[#This Row],[Total]]*urbanthreads_q4[[#This Row],[Disc %]]/100 -> 899.8 | Z76: =urbanthreads_q4[[#This Row],[Total]]-urbanthreads_q4[[#This Row],[Disc %]] -> 4479 | AA76: =urbanthreads_q4[[#This Row],[Net revenue]]/urbanthreads_q4[[#This Row],[Total]] -> 0.99555457 | AB76: =TEXT(urbanthreads_q4[[#This Row],[Order Date]],"mm-yyyy") -> 12-2024 | AC76: =YEAR(urbanthreads_q4[[#This Row],[Order Date]]) & "-W" & WEEKNUM(urbanthreads_q4[[#This Row],[Order Date]], 2) -> 2024-W51 | AD76: =IF(urbanthreads_q4[[#This Row],[Payment]]="COD","COD","Prepaid") -> Prepaid
A77: UT-100076 | B77: 45584 | C77: CUST_10075 | D77: New | E77: DRS-SMK-S | F77: Dresses | G77: Smocked Dress | H77: 2199 | I77: 1 | J77: 2199 | L77: 0 | M77: Credit Card | N77: Instagram Shop | O77: Patna | P77: Bihar | Q77: Delhi | R77: 45596 | S77: Delivered | T77: No | W77: Not Applicable | X77: =IF(urbanthreads_q4[[#This Row],[Qty]]>0,"Valid","Invalid") -> Valid | Y77: =urbanthreads_q4[[#This Row],[Total]]*urbanthreads_q4[[#This Row],[Disc %]]/100 -> 0 | Z77: =urbanthreads_q4[[#This Row],[Total]]-urbanthreads_q4[[#This Row],[Disc %]] -> 2199 | AA77: =urbanthreads_q4[[#This Row],[Net revenue]]/urbanthreads_q4[[#This Row],[Total]] -> 1 | AB77: =TEXT(urbanthreads_q4[[#This Row],[Order Date]],"mm-yyyy") -> 10-2024 | AC77: =YEAR(urbanthreads_q4[[#This Row],[Order Date]]) & "-W" & WEEKNUM(urbanthreads_q4[[#This Row],[Order Date]], 2) -> 2024-W42 | AD77: =IF(urbanthreads_q4[[#This Row],[Payment]]="COD","COD","Prepaid") -> Prepaid
A78: UT-100303 | B78: 45646 | C78: CUST_10302 | D78: New | E78: OUT-HOL-M | F78: Outerwear | G78: Holiday Jacket | H78: 5199 | I78: 1 | J78: 5199 | L78: 0 | M78: COD | N78: Instagram Shop | O78: Rajkot | P78: Gujarat | Q78: Mumbai | R78: 45668 | S78: Delivered | T78: Yes | U78: Wrong Item | V78: 45696 | W78: Processed | X78: =IF(urbanthreads_q4[[#This Row],[Qty]]>0,"Valid","Invalid") -> Valid | Y78: =urbanthreads_q4[[#This Row],[Total]]*urbanthreads_q4[[#This Row],[Disc %]]/100 -> 0 | Z78: =urbanthreads_q4[[#This Row],[Total]]-urbanthreads_q4[[#This Row],[Disc %]] -> 5199 | AA78: =urbanthreads_q4[[#This Row],[Net revenue]]/urbanthreads_q4[[#This Row],[Total]] -> 1 | AB78: =TEXT(urbanthreads_q4[[#This Row],[Order Date]],"mm-yyyy") -> 12-2024 | AC78: =YEAR(urbanthreads_q4[[#This Row],[Order Date]]) & "-W" & WEEKNUM(urbanthreads_q4[[#This Row],[Order Date]], 2) -> 2024-W51 | AD78: =IF(urbanthreads_q4[[#This Row],[Payment]]="COD","COD","Prepaid") -> COD
A79: UT-100078 | B79: 45584 | C79: CUST_10077 | D79: Returning | E79: OUT-VLV-L | F79: Outerwear | G79: Velvet Blazer | H79: 4999 | I79: 1 | J79: 4999 | L79: 0 | M79: UPI | N79: Website | O79: Nagpur | P79: Maharashtra | Q79: Mumbai | R79: 45597 | S79: Delivered | T79: No | W79: Not Applicable | X79: =IF(urbanthreads_q4[[#This Row],[Qty]]>0,"Valid","Invalid") -> Valid | Y79: =urbanthreads_q4[[#This Row],[Total]]*urbanthreads_q4[[#This Row],[Disc %]]/100 -> 0 | Z79: =urbanthreads_q4[[#This Row],[Total]]-urbanthreads_q4[[#This Row],[Disc %]] -> 4999 | AA79: =urbanthreads_q4[[#This Row],[Net revenue]]/urbanthreads_q4[[#This Row],[Total]] -> 1 | AB79: =TEXT(urbanthreads_q4[[#This Row],[Order Date]],"mm-yyyy") -> 10-2024 | AC79: =YEAR(urbanthreads_q4[[#This Row],[Order Date]]) & "-W" & WEEKNUM(urbanthreads_q4[[#This Row],[Order Date]], 2) -> 2024-W42 | AD79: =IF(urbanthreads_q4[[#This Row],[Payment]]="COD","COD","Prepaid") -> Prepaid
A80: UT-100305 | B80: 45646 | C80: CUST_10304 | D80: New | E80: TOP-SNW-L | F80: Tops | G80: Snow White Top | H80: 2099 | I80: 1 | J80: 2099 | L80: 0 | M80: Debit Card | N80: Mobile App | O80: Mumbai | P80: Maharashtra | Q80: Mumbai | R80: 45668 | S80: Delivered | T80: Yes | U80: Damaged in Transit | V80: 45695 | W80: Processed | X80: =IF(urbanthreads_q4[[#This Row],[Qty]]>0,"Valid","Invalid") -> Valid | Y80: =urbanthreads_q4[[#This Row],[Total]]*urbanthreads_q4[[#This Row],[Disc %]]/100 -> 0 | Z80: =urbanthreads_q4[[#This Row],[Total]]-urbanthreads_q4[[#This Row],[Disc %]] -> 2099 | AA80: =urbanthreads_q4[[#This Row],[Net revenue]]/urbanthreads_q4[[#This Row],[Total]] -> 1 | AB80: =TEXT(urbanthreads_q4[[#This Row],[Order Date]],"mm-yyyy") -> 12-2024 | AC80: =YEAR(urbanthreads_q4[[#This Row],[Order Date]]) & "-W" & WEEKNUM(urbanthreads_q4[[#This Row],[Order Date]], 2) -> 2024-W51 | AD80: =IF(urbanthreads_q4[[#This Row],[Payment]]="COD","COD","Prepaid") -> Prepaid
A81: UT-100080 | B81: 45585 | C81: CUST_10079 | D81: New | E81: BOT-CRG-S | F81: Bottoms | G81: Cargo Shorts | H81: 1499 | I81: 1 | J81: 1499 | K81: DIWALI20 | L81: 20 | M81: Credit Card | N81: Mobile App | O81: Kochi | P81: Kerala | Q81: Bangalore | R81: 45596 | S81: Delivered | T81: No | W81: Not Applicable | X81: =IF(urbanthreads_q4[[#This Row],[Qty]]>0,"Valid","Invalid") -> Valid | Y81: =urbanthreads_q4[[#This Row],[Total]]*urbanthreads_q4[[#This Row],[Disc %]]/100 -> 299.8 | Z81: =urbanthreads_q4[[#This Row],[Total]]-urbanthreads_q4[[#This Row],[Disc %]] -> 1479 | AA81: =urbanthreads_q4[[#This Row],[Net revenue]]/urbanthreads_q4[[#This Row],[Total]] -> 0.98665777 | AB81: =TEXT(urbanthreads_q4[[#This Row],[Order Date]],"mm-yyyy") -> 10-2024 | AC81: =YEAR(urbanthreads_q4[[#This Row],[Order Date]]) & "-W" & WEEKNUM(urbanthreads_q4[[#This Row],[Order Date]], 2) -> 2024-W42 | AD81: =IF(urbanthreads_q4[[#This Row],[Payment]]="COD","COD","Prepaid") -> Prepaid
A82: UT-100306 | B82: 45647 | C82: CUST_10305 | D82: New | E82: DRS-ICE-S | F82: Dresses | G82: Ice Queen Dress | H82: 3999 | I82: 1 | J82: 3999 | L82: 0 | M82: Credit Card | N82: Instagram Shop | O82: Delhi | P82: Delhi | Q82: Delhi | R82: 45669 | S82: Delivered | T82: Yes | U82: Size Issue | V82: 45697 | W82: Processed | X82: =IF(urbanthreads_q4[[#This Row],[Qty]]>0,"Valid","Invalid") -> Valid | Y82: =urbanthreads_q4[[#This Row],[Total]]*urbanthreads_q4[[#This Row],[Disc %]]/100 -> 0 | Z82: =urbanthreads_q4[[#This Row],[Total]]-urbanthreads_q4[[#This Row],[Disc %]] -> 3999 | AA82: =urbanthreads_q4[[#This Row],[Net revenue]]/urbanthreads_q4[[#This Row],[Total]] -> 1 | AB82: =TEXT(urbanthreads_q4[[#This Row],[Order Date]],"mm-yyyy") -> 12-2024 | AC82: =YEAR(urbanthreads_q4[[#This Row],[Order Date]]) & "-W" & WEEKNUM(urbanthreads_q4[[#This Row],[Order Date]], 2) -> 2024-W51 | AD82: =IF(urbanthreads_q4[[#This Row],[Payment]]="COD","COD","Prepaid") -> Prepaid
A83: UT-100082 | B83: 45585 | C83: CUST_10081 | D83: Returning | E83: TOP-VNK-L | F83: Tops | G83: V-Neck Tee | H83: 1099 | I83: 2 | J83: 2198 | L83: 0 | M83: UPI | N83: Instagram Shop | O83: Thiruvananthapuram | P83: Kerala | Q83: Bangalore | R83: 45595 | S83: Delivered | T83: No | W83: Not Applicable | X83: =IF(urbanthreads_q4[[#This Row],[Qty]]>0,"Valid","Invalid") -> Valid | Y83: =urbanthreads_q4[[#This Row],[Total]]*urbanthreads_q4[[#This Row],[Disc %]]/100 -> 0 | Z83: =urbanthreads_q4[[#This Row],[Total]]-urbanthreads_q4[[#This Row],[Disc %]] -> 2198 | AA83: =urbanthreads_q4[[#This Row],[Net revenue]]/urbanthreads_q4[[#This Row],[Total]] -> 1 | AB83: =TEXT(urbanthreads_q4[[#This Row],[Order Date]],"mm-yyyy") -> 10-2024 | AC83: =YEAR(urbanthreads_q4[[#This Row],[Order Date]]) & "-W" & WEEKNUM(urbanthreads_q4[[#This Row],[Order Date]], 2) -> 2024-W42 | AD83: =IF(urbanthreads_q4[[#This Row],[Payment]]="COD","COD","Prepaid") -> Prepaid
A84: UT-100308 | B84: 45647 | C84: CUST_10307 | D84: New | E84: OUT-WNT-L | F84: Outerwear | G84: Winter Wonderland Coat | H84: 7299 | I84: 1 | J84: 7299 | L84: 0 | M84: COD | N84: Mobile App | O84: Chennai | P84: Tamil Nadu | Q84: Bangalore | R84: 45670 | S84: Delivered | T84: Yes | U84: Changed Mind | V84: 45698 | W84: Processed | X84: =IF(urbanthreads_q4[[#This Row],[Qty]]>0,"Valid","Invalid") -> Valid | Y84: =urbanthreads_q4[[#This Row],[Total]]*urbanthreads_q4[[#This Row],[Disc %]]/100 -> 0 | Z84: =urbanthreads_q4[[#This Row],[Total]]-urbanthreads_q4[[#This Row],[Disc %]] -> 7299 | AA84: =urbanthreads_q4[[#This Row],[Net revenue]]/urbanthreads_q4[[#This Row],[Total]] -> 1 | AB84: =TEXT(urbanthreads_q4[[#This Row],[Order Date]],"mm-yyyy") -> 12-2024 | AC84: =YEAR(urbanthreads_q4[[#This Row],[Order Date]]) & "-W" & WEEKNUM(urbanthreads_q4[[#This Row],[Order Date]], 2) -> 2024-W51 | AD84: =IF(urbanthreads_q4[[#This Row],[Payment]]="COD","COD","Prepaid") -> COD
A85: UT-100084 | B85: 45586 | C85: CUST_10083 | D85: New | E85: ACC-BDY-OS | F85: Accessories | G85: Body Chain | H85: 799 | I85: 1 | J85: 799 | L85: 0 | M85: COD | N85: Website | O85: Vadodara | P85: Gujarat | Q85: Mumbai | S85: RTO | T85: No | W85: Not Applicable | X85: =IF(urbanthreads_q4[[#This Row],[Qty]]>0,"Valid","Invalid") -> Valid | Y85: =urbanthreads_q4[[#This Row],[Total]]*urbanthreads_q4[[#This Row],[Disc %]]/100 -> 0 | Z85: =urbanthreads_q4[[#This Row],[Total]]-urbanthreads_q4[[#This Row],[Disc %]] -> 799 | AA85: =urbanthreads_q4[[#This Row],[Net revenue]]/urbanthreads_q4[[#This Row],[Total]] -> 1 | AB85: =TEXT(urbanthreads_q4[[#This Row],[Order Date]],"mm-yyyy") -> 10-2024 | AC85: =YEAR(urbanthreads_q4[[#This Row],[Order Date]]) & "-W" & WEEKNUM(urbanthreads_q4[[#This Row],[Order Date]], 2) -> 2024-W43 | AD85: =IF(urbanthreads_q4[[#This Row],[Payment]]="COD","COD","Prepaid") -> COD
A86: UT-100085 | B86: 45586 | C86: CUST_10084 | D86: New | E86: BOT-JGR-L | F86: Bottoms | G86: Jogger Pants | H86: 1599 | I86: 1 | J86: 1599 | L86: 0 | M86: Wallet | N86: Instagram Shop | O86: Rajkot | P86: Gujarat | Q86: Mumbai | R86: 45598 | S86: Delivered | T86: No | W86: Not Applicable | X86: =IF(urbanthreads_q4[[#This Row],[Qty]]>0,"Valid","Invalid") -> Valid | Y86: =urbanthreads_q4[[#This Row],[Total]]*urbanthreads_q4[[#This Row],[Disc %]]/100 -> 0 | Z86: =urbanthreads_q4[[#This Row],[Total]]-urbanthreads_q4[[#This Row],[Disc %]] -> 1599 | AA86: =urbanthreads_q4[[#This Row],[Net revenue]]/urbanthreads_q4[[#This Row],[Total]] -> 1 | AB86: =TEXT(urbanthreads_q4[[#This Row],[Order Date]],"mm-yyyy") -> 10-2024 | AC86: =YEAR(urbanthreads_q4[[#This Row],[Order Date]]) & "-W" & WEEKNUM(urbanthreads_q4[[#This Row],[Order Date]], 2) -> 2024-W43 | AD86: =IF(urbanthreads_q4[[#This Row],[Payment]]="COD","COD","Prepaid") -> Prepaid
A87: UT-100309 | B87: 45647 | C87: CUST_10308 | D87: Returning | E87: ACC-SNF-OS | F87: Accessories | G87: Snowflake Pendant | H87: 899 | I87: 1 | J87: 899 | L87: 0 | M87: Wallet | N87: Instagram Shop | O87: Hyderabad | P87: Telangana | Q87: Bangalore | R87: 45669 | S87: Delivered | T87: Yes | U87: Quality Defect | V87: 45696 | W87: Processed | X87: =IF(urbanthreads_q4[[#This Row],[Qty]]>0,"Valid","Invalid") -> Valid | Y87: =urbanthreads_q4[[#This Row],[Total]]*urbanthreads_q4[[#This Row],[Disc %]]/100 -> 0 | Z87: =urbanthreads_q4[[#This Row],[Total]]-urbanthreads_q4[[#This Row],[Disc %]] -> 899 | AA87: =urbanthreads_q4[[#This Row],[Net revenue]]/urbanthreads_q4[[#This Row],[Total]] -> 1 | AB87: =TEXT(urbanthreads_q4[[#This Row],[Order Date]],"mm-yyyy") -> 12-2024 | AC87: =YEAR(urbanthreads_q4[[#This Row],[Order Date]]) & "-W" & WEEKNUM(urbanthreads_q4[[#This Row],[Order Date]], 2) -> 2024-W51 | AD87: =IF(urbanthreads_q4[[#This Row],[Payment]]="COD","COD","Prepaid") -> Prepaid
A88: UT-100087 | B88: 45586 | C88: CUST_10086 | D88: New | E88: TOP-SQR-M | F88: Tops | G88: Square Neck Top | H88: 1499 | I88: 1 | J88: 1499 | L88: 0 | M88: UPI | N88: Website | O88: Mumbai | P88: Maharashtra | Q88: Mumbai | R88: 45598 | S88: Delivered | T88: No | W88: Not Applicable | X88: =IF(urbanthreads_q4[[#This Row],[Qty]]>0,"Valid","Invalid") -> Valid | Y88: =urbanthreads_q4[[#This Row],[Total]]*urbanthreads_q4[[#This Row],[Disc %]]/100 -> 0 | Z88: =urbanthreads_q4[[#This Row],[Total]]-urbanthreads_q4[[#This Row],[Disc %]] -> 1499 | AA88: =urbanthreads_q4[[#This Row],[Net revenue]]/urbanthreads_q4[[#This Row],[Total]] -> 1 | AB88: =TEXT(urbanthreads_q4[[#This Row],[Order Date]],"mm-yyyy") -> 10-2024 | AC88: =YEAR(urbanthreads_q4[[#This Row],[Order Date]]) & "-W" & WEEKNUM(urbanthreads_q4[[#This Row],[Order Date]], 2) -> 2024-W43 | AD88: =IF(urbanthreads_q4[[#This Row],[Payment]]="COD","COD","Prepaid") -> Prepaid
A89: UT-100311 | B89: 45648 | C89: CUST_10310 | D89: New | E89: DRS-NYR-L | F89: Dresses | G89: New Year Ready Dress | H89: 4699 | I89: 1 | J89: 4699 | L89: 0 | M89: Credit Card | N89: Mobile App | O89: Ahmedabad | P89: Gujarat | Q89: Mumbai | R89: 45671 | S89: Delivered | T89: Yes | U89: Size Issue | V89: 45699 | W89: Processed | X89: =IF(urbanthreads_q4[[#This Row],[Qty]]>0,"Valid","Invalid") -> Valid | Y89: =urbanthreads_q4[[#This Row],[Total]]*urbanthreads_q4[[#This Row],[Disc %]]/100 -> 0 | Z89: =urbanthreads_q4[[#This Row],[Total]]-urbanthreads_q4[[#This Row],[Disc %]] -> 4699 | AA89: =urbanthreads_q4[[#This Row],[Net revenue]]/urbanthreads_q4[[#This Row],[Total]] -> 1 | AB89: =TEXT(urbanthreads_q4[[#This Row],[Order Date]],"mm-yyyy") -> 12-2024 | AC89: =YEAR(urbanthreads_q4[[#This Row],[Order Date]]) & "-W" & WEEKNUM(urbanthreads_q4[[#This Row],[Order Date]], 2) -> 2024-W51 | AD89: =IF(urbanthreads_q4[[#This Row],[Payment]]="COD","COD","Prepaid") -> Prepaid
A90: UT-100089 | B90: 45587 | C90: CUST_10088 | D90: New | E90: ACC-ANK-OS | F90: Accessories | G90: Anklet | H90: 499 | I90: 2 | J90: 998 | K90: FLAT10 | L90: 10 | M90: Credit Card | N90: Mobile App | O90: Kolkata | P90: West Bengal | Q90: Delhi | R90: 45597 | S90: Delivered | T90: No | W90: Not Applicable | X90: =IF(urbanthreads_q4[[#This Row],[Qty]]>0,"Valid","Invalid") -> Valid | Y90: =urbanthreads_q4[[#This Row],[Total]]*urbanthreads_q4[[#This Row],[Disc %]]/100 -> 99.8 | Z90: =urbanthreads_q4[[#This Row],[Total]]-urbanthreads_q4[[#This Row],[Disc %]] -> 988 | AA90: =urbanthreads_q4[[#This Row],[Net revenue]]/urbanthreads_q4[[#This Row],[Total]] -> 0.98997996 | AB90: =TEXT(urbanthreads_q4[[#This Row],[Order Date]],"mm-yyyy") -> 10-2024 | AC90: =YEAR(urbanthreads_q4[[#This Row],[Order Date]]) & "-W" & WEEKNUM(urbanthreads_q4[[#This Row],[Order Date]], 2) -> 2024-W43 | AD90: =IF(urbanthreads_q4[[#This Row],[Payment]]="COD","COD","Prepaid") -> Prepaid
A91: UT-100090 | B91: 45587 | C91: CUST_10089 | D91: Returning | E91: BOT-TRS-M | F91: Bottoms | G91: Tailored Trousers | H91: 2399 | I91: 1 | J91: 2399 | L91: 0 | M91: UPI | N91: Website | O91: Chennai | P91: Tamil Nadu | Q91: Bangalore | R91: 45599 | S91: Delivered | T91: No | W91: Not Applicable | X91: =IF(urbanthreads_q4[[#This Row],[Qty]]>0,"Valid","Invalid") -> Valid | Y91: =urbanthreads_q4[[#This Row],[Total]]*urbanthreads_q4[[#This Row],[Disc %]]/100 -> 0 | Z91: =urbanthreads_q4[[#This Row],[Total]]-urbanthreads_q4[[#This Row],[Disc %]] -> 2399 | AA91: =urbanthreads_q4[[#This Row],[Net revenue]]/urbanthreads_q4[[#This Row],[Total]] -> 1 | AB91: =TEXT(urbanthreads_q4[[#This Row],[Order Date]],"mm-yyyy") -> 10-2024 | AC91: =YEAR(urbanthreads_q4[[#This Row],[Order Date]]) & "-W" & WEEKNUM(urbanthreads_q4[[#This Row],[Order Date]], 2) -> 2024-W43 | AD91: =IF(urbanthreads_q4[[#This Row],[Payment]]="COD","COD","Prepaid") -> Prepaid
A92: UT-100091 | B92: 45587 | C92: CUST_10090 | D92: New | E92: DRS-LST-M | F92: Dresses | G92: Lace Trim Dress | H92: 2599 | I92: 1 | J92: 2599 | L92: 0 | M92: COD | N92: Instagram Shop | O92: Hyderabad | P92: Telangana | Q92: Bangalore | S92: RTO | T92: No | W92: Not Applicable | X92: =IF(urbanthreads_q4[[#This Row],[Qty]]>0,"Valid","Invalid") -> Valid | Y92: =urbanthreads_q4[[#This Row],[Total]]*urbanthreads_q4[[#This Row],[Disc %]]/100 -> 0 | Z92: =urbanthreads_q4[[#This Row],[Total]]-urbanthreads_q4[[#This Row],[Disc %]] -> 2599 | AA92: =urbanthreads_q4[[#This Row],[Net revenue]]/urbanthreads_q4[[#This Row],[Total]] -> 1 | AB92: =TEXT(urbanthreads_q4[[#This Row],[Order Date]],"mm-yyyy") -> 10-2024 | AC92: =YEAR(urbanthreads_q4[[#This Row],[Order Date]]) & "-W" & WEEKNUM(urbanthreads_q4[[#This Row],[Order Date]], 2) -> 2024-W43 | AD92: =IF(urbanthreads_q4[[#This Row],[Payment]]="COD","COD","Prepaid") -> COD
A93: UT-100313 | B93: 45648 | C93: CUST_10312 | D93: New | E93: OUT-CEL-M | F93: Outerwear | G93: Celebrate Blazer | H93: 5399 | I93: 1 | J93: 5399 | K93: Dec20 | L93: 20 | M93: COD | N93: Website | O93: Lucknow | P93: Uttar Pradesh | Q93: Delhi | R93: 45672 | S93: Delivered | T93: Yes | U93: Wrong Item | V93: 45700 | W93: Processed | X93: =IF(urbanthreads_q4[[#This Row],[Qty]]>0,"Valid","Invalid") -> Valid | Y93: =urbanthreads_q4[[#This Row],[Total]]*urbanthreads_q4[[#This Row],[Disc %]]/100 -> 1079.8 | Z93: =urbanthreads_q4[[#This Row],[Total]]-urbanthreads_q4[[#This Row],[Disc %]] -> 5379 | AA93: =urbanthreads_q4[[#This Row],[Net revenue]]/urbanthreads_q4[[#This Row],[Total]] -> 0.99629561 | AB93: =TEXT(urbanthreads_q4[[#This Row],[Order Date]],"mm-yyyy") -> 12-2024 | AC93: =YEAR(urbanthreads_q4[[#This Row],[Order Date]]) & "-W" & WEEKNUM(urbanthreads_q4[[#This Row],[Order Date]], 2) -> 2024-W51 | AD93: =IF(urbanthreads_q4[[#This Row],[Payment]]="COD","COD","Prepaid") -> COD
A94: UT-100093 | B94: 45588 | C94: CUST_10092 | D94: New | E94: OUT-PUF-M | F94: Outerwear | G94: Puffer Jacket | H94: 4299 | I94: 1 | J94: 4299 | L94: 0 | M94: Credit Card | N94: Website | O94: Ahmedabad | P94: Gujarat | Q94: Mumbai | R94: 45601 | S94: Delivered | T94: No | W94: Not Applicable | X94: =IF(urbanthreads_q4[[#This Row],[Qty]]>0,"Valid","Invalid") -> Valid | Y94: =urbanthreads_q4[[#This Row],[Total]]*urbanthreads_q4[[#This Row],[Disc %]]/100 -> 0 | Z94: =urbanthreads_q4[[#This Row],[Total]]-urbanthreads_q4[[#This Row],[Disc %]] -> 4299 | AA94: =urbanthreads_q4[[#This Row],[Net revenue]]/urbanthreads_q4[[#This Row],[Total]] -> 1 | AB94: =TEXT(urbanthreads_q4[[#This Row],[Order Date]],"mm-yyyy") -> 10-2024 | AC94: =YEAR(urbanthreads_q4[[#This Row],[Order Date]]) & "-W" & WEEKNUM(urbanthreads_q4[[#This Row],[Order Date]], 2) -> 2024-W43 | AD94: =IF(urbanthreads_q4[[#This Row],[Payment]]="COD","COD","Prepaid") -> Prepaid
A95: UT-100094 | B95: 45588 | C95: CUST_10093 | D95: Returning | E95: ACC-HDR-OS | F95: Accessories | G95: Hairband | H95: 399 | I95: 3 | J95: 1197 | L95: 0 | M95: UPI | N95: Instagram Shop | O95: Jaipur | P95: Rajasthan | Q95: Delhi | R95: 45598 | S95: Delivered | T95: No | W95: Not Applicable | X95: =IF(urbanthreads_q4[[#This Row],[Qty]]>0,"Valid","Invalid") -> Valid | Y95: =urbanthreads_q4[[#This Row],[Total]]*urbanthreads_q4[[#This Row],[Disc %]]/100 -> 0 | Z95: =urbanthreads_q4[[#This Row],[Total]]-urbanthreads_q4[[#This Row],[Disc %]] -> 1197 | AA95: =urbanthreads_q4[[#This Row],[Net revenue]]/urbanthreads_q4[[#This Row],[Total]] -> 1 | AB95: =TEXT(urbanthreads_q4[[#This Row],[Order Date]],"mm-yyyy") -> 10-2024 | AC95: =YEAR(urbanthreads_q4[[#This Row],[Order Date]]) & "-W" & WEEKNUM(urbanthreads_q4[[#This Row],[Order Date]], 2) -> 2024-W43 | AD95: =IF(urbanthreads_q4[[#This Row],[Payment]]="COD","COD","Prepaid") -> Prepaid
A96: UT-100258 | B96: 45635 | C96: CUST_10257 | D96: Returning | E96: OUT-SQN-M | F96: Outerwear | G96: Sequin Jacket | H96: 5999 | I96: 1 | J96: 5999 | L96: 0 | M96: COD | N96: Instagram Shop | O96: Kanpur | P96: Uttar Pradesh | Q96: Delhi | R96: 45650 | S96: Delivered | T96: Yes | U96: Changed Mind | V96: 45677 | W96: Processed | X96: =IF(urbanthreads_q4[[#This Row],[Qty]]>0,"Valid","Invalid") -> Valid | Y96: =urbanthreads_q4[[#This Row],[Total]]*urbanthreads_q4[[#This Row],[Disc %]]/100 -> 0 | Z96: =urbanthreads_q4[[#This Row],[Total]]-urbanthreads_q4[[#This Row],[Disc %]] -> 5999 | AA96: =urbanthreads_q4[[#This Row],[Net revenue]]/urbanthreads_q4[[#This Row],[Total]] -> 1 | AB96: =TEXT(urbanthreads_q4[[#This Row],[Order Date]],"mm-yyyy") -> 12-2024 | AC96: =YEAR(urbanthreads_q4[[#This Row],[Order Date]]) & "-W" & WEEKNUM(urbanthreads_q4[[#This Row],[Order Date]], 2) -> 2024-W50 | AD96: =IF(urbanthreads_q4[[#This Row],[Payment]]="COD","COD","Prepaid") -> COD
A97: UT-100096 | B97: 45589 | C97: CUST_10095 | D97: New | E97: DRS-SHR-S | F97: Dresses | G97: Shirtdress | H97: 2399 | I97: 1 | J97: 2399 | L97: 0 | M97: Credit Card | N97: Website | O97: Bangalore | P97: Karnataka | Q97: Bangalore | R97: 45600 | S97: Delivered | T97: No | W97: Not Applicable | X97: =IF(urbanthreads_q4[[#This Row],[Qty]]>0,"Valid","Invalid") -> Valid | Y97: =urbanthreads_q4[[#This Row],[Total]]*urbanthreads_q4[[#This Row],[Disc %]]/100 -> 0 | Z97: =urbanthreads_q4[[#This Row],[Total]]-urbanthreads_q4[[#This Row],[Disc %]] -> 2399 | AA97: =urbanthreads_q4[[#This Row],[Net revenue]]/urbanthreads_q4[[#This Row],[Total]] -> 1 | AB97: =TEXT(urbanthreads_q4[[#This Row],[Order Date]],"mm-yyyy") -> 10-2024 | AC97: =YEAR(urbanthreads_q4[[#This Row],[Order Date]]) & "-W" & WEEKNUM(urbanthreads_q4[[#This Row],[Order Date]], 2) -> 2024-W43 | AD97: =IF(urbanthreads_q4[[#This Row],[Payment]]="COD","COD","Prepaid") -> Prepaid
A98: UT-100260 | B98: 45635 | C98: CUST_10259 | D98: New | E98: TOP-FTH-S | F98: Tops | G98: Feather Trim Top | H98: 2099 | I98: 1 | J98: 2099 | L98: 0 | M98: Debit Card | N98: Mobile App | O98: Delhi | P98: Delhi | Q98: Delhi | R98: 45650 | S98: Delivered | T98: Yes | U98: Quality Defect | V98: 45676 | W98: Processed | X98: =IF(urbanthreads_q4[[#This Row],[Qty]]>0,"Valid","Invalid") -> Valid | Y98: =urbanthreads_q4[[#This Row],[Total]]*urbanthreads_q4[[#This Row],[Disc %]]/100 -> 0 | Z98: =urbanthreads_q4[[#This Row],[Total]]-urbanthreads_q4[[#This Row],[Disc %]] -> 2099 | AA98: =urbanthreads_q4[[#This Row],[Net revenue]]/urbanthreads_q4[[#This Row],[Total]] -> 1 | AB98: =TEXT(urbanthreads_q4[[#This Row],[Order Date]],"mm-yyyy") -> 12-2024 | AC98: =YEAR(urbanthreads_q4[[#This Row],[Order Date]]) & "-W" & WEEKNUM(urbanthreads_q4[[#This Row],[Order Date]], 2) -> 2024-W50 | AD98: =IF(urbanthreads_q4[[#This Row],[Payment]]="COD","COD","Prepaid") -> Prepaid
A99: UT-100098 | B99: 45589 | C99: CUST_10097 | D99: Returning | E99: OUT-SHW-L | F99: Outerwear | G99: Shawl Wrap | H99: 2799 | I99: 1 | J99: 2799 | K99: DIWALI20 | L99: 20 | M99: UPI | N99: Mobile App | O99: Delhi | P99: Delhi | Q99: Delhi | R99: 45601 | S99: Delivered | T99: No | W99: Not Applicable | X99: =IF(urbanthreads_q4[[#This Row],[Qty]]>0,"Valid","Invalid") -> Valid | Y99: =urbanthreads_q4[[#This Row],[Total]]*urbanthreads_q4[[#This Row],[Disc %]]/100 -> 559.8 | Z99: =urbanthreads_q4[[#This Row],[Total]]-urbanthreads_q4[[#This Row],[Disc %]] -> 2779 | AA99: =urbanthreads_q4[[#This Row],[Net revenue]]/urbanthreads_q4[[#This Row],[Total]] -> 0.99285459 | AB99: =TEXT(urbanthreads_q4[[#This Row],[Order Date]],"mm-yyyy") -> 10-2024 | AC99: =YEAR(urbanthreads_q4[[#This Row],[Order Date]]) & "-W" & WEEKNUM(urbanthreads_q4[[#This Row],[Order Date]], 2) -> 2024-W43 | AD99: =IF(urbanthreads_q4[[#This Row],[Payment]]="COD","COD","Prepaid") -> Prepaid
A100: UT-100099 | B100: 45589 | C100: CUST_10098 | D100: New | E100: ACC-BLT-S | F100: Accessories | G100: Braided Belt | H100: 699 | I100: 1 | J100: 699 | L100: 0 | M100: Wallet | N100: Website | O100: Chandigarh | P100: Punjab | Q100: Delhi | R100: 45600 | S100: Delivered | T100: No | W100: Not Applicable | X100: =IF(urbanthreads_q4[[#This Row],[Qty]]>0,"Valid","Invalid") -> Valid | Y100: =urbanthreads_q4[[#This Row],[Total]]*urbanthreads_q4[[#This Row],[Disc %]]/100 -> 0 | Z100: =urbanthreads_q4[[#This Row],[Total]]-urbanthreads_q4[[#This Row],[Disc %]] -> 699 | AA100: =urbanthreads_q4[[#This Row],[Net revenue]]/urbanthreads_q4[[#This Row],[Total]] -> 1 | AB100: =TEXT(urbanthreads_q4[[#This Row],[Order Date]],"mm-yyyy") -> 10-2024 | AC100: =YEAR(urbanthreads_q4[[#This Row],[Order Date]]) & "-W" & WEEKNUM(urbanthreads_q4[[#This Row],[Order Date]], 2) -> 2024-W43 | AD100: =IF(urbanthreads_q4[[#This Row],[Payment]]="COD","COD","Prepaid") -> Prepaid
...

Sheet Cleaning_log
A1: Issue Type | B1: Column Name | C1: Example | D1: Why | E1: Expected or Error | F1: Action
A2: Missing Value | B2: Deivery_date | C2: RTO orders | D2: Delivery never completed | E2: Expected | F2: Left Blank
A3: Missing Value | B3: Return_reason | C3: RTO orders | D3: RTO orders never reach customers,so no returns exist | E3: Expected | F3: Left Blank
A4: Missing Value | B4: Return_recieved | C4: RTO orders | D4: Items returned to warehouse without customer return | E4: Expected | F4: Left Blank
A5: Duplicate Check | B5: Order ID | C5: All Rows | D5: Each order_id is unique | E5: Expected | F5: No action Needed
A6: Format Inconsistency | B6: Delivery Status | C6: "Delievered" | D6: Typo error | E6: Error | F6: Fixed the typo mistake with find and replace method
A7: Format Check | B7: Multiple text columns | C7: delivery_status,payment_method etc | D7: Checked for spelling,spaces etc | E7: Expected | F7: No futher action needed
A8: Outlier Issue | B8: Quantity | C8: -1 | D8: Quantity cannot be in negative | E8: Error | F8: Flagged and excluded from KPI calculations
A9: Outlier / Logical issue | B9: Quantity

Sheet Validation_summary
A1: Rule ID | B1: Validation Check | C1: Result | D1: Notes
A2: V1 | B2: order_id format UT-XXXXXX | C2: Pass | D2: All IDs consistent
A3: V2 | B3: customer_type values | C3: Pass | D3: New / Returning only
A4: V3 | B4: quantity positive integer | C4: Fail | D4: -1 flagged & excluded
A5: V4 | B5: discount_percent 0–100 | C5: Pass | D5: No outliers
A6: V5 | B6: order_date in Q4 2024 | C6: Pass | D6: All dates in range
A7: V6 | B7: payment_method valid | C7: Pass | D7: No invalid methods
A8: V7 | B8: Delivered → delivery_date | C8: Pass | D8: No missing dates
A9: V8 | B9: No return → blank reason | C9: Pass | D9: Business logic OK
A10: V9 | B10: warehouse_origin valid | C10: Pass | D10: Mumbai/Delhi/Bangalore
A11: V10 | B11: refund_status logic | C11: Pass | D11: Consistent

Sheet Working_Analysis
A3: Row Labels | B3: Count of Order ID | D3: Row Labels | E3: Sum of Discount_amount
A4: Valid | B4: 345 | D4: Valid | E4: 114181.65
A5: Grand Total | B5: 345 | D5: Grand Total | E5: 114181.65
A7: Row Labels | B7: Sum of Qty
A8: Valid | B8: 410 | D8: Row Labels | E8: Count of Order ID
A9: Grand Total | B9: 410 | D9: Valid
D10: Delivered | E10: 327
A11: Row Labels | B11: Sum of Total | D11: Grand Total | E11: 327
A12: Valid | B12: 1018790
A13: Grand Total | B13: 1018790 | D13: Total Delivered Orders | E13: =COUNTIFS(urbanthreads_q4[Status],"Delivered") -> 328 | F13: (Overall Return Rate)
D14: Returned Delivered Orders | E14: =COUNTIFS( urbanthreads_q4[Status], "Delivered", urbanthreads_q4[Return?], "Yes" ) -> 180
D15: Order Return Rate | E15: =E14/E13 -> 0.54878049
D17: Row Labels | E17: Count of Order ID | F17: (Monthly order volume)
D18: 01-2024 | E18: 1
D19: 10-2024 | E19: 131
D20: 11-2024 | E20: 93
D21: 12-2024 | E21: 121 | J21: Status | K21: Delivered
D22: Grand Total | E22: 346 | G22: Status | H22: Delivered | J22: Return? | K22: Yes
D23: Weekly Trend Analysis
D24: Week Number | E24: Total Orders (By week) | G24: Week Number | H24: Total Orders Delivered | J24: Week Number | K24: Returned Delivered Orders
D25: 2024-W2 | E25: 1 | G25: 2024-W2 | H25: 1 | J25: 2024-W40 | K25: 11
D26: 2024-W40 | E26: 26 | G26: 2024-W40 | H26: 23 | J26: 2024-W41 | K26: 11
D27: 2024-W41 | E27: 29 | G27: 2024-W41 | H27: 27 | J27: 2024-W42 | K27: 13
D28: 2024-W42 | E28: 28 | G28: 2024-W42 | H28: 26 | J28: 2024-W43 | K28: 10
D29: 2024-W43 | E29: 27 | G29: 2024-W43 | H29: 24 | J29: 2024-W44 | K29: 24
D30: 2024-W44 | E30: 33 | F30: (Diwali spike -Yes) | G30: 2024-W44 | H30: 31 | J30: 2024-W45 | K30: 11
D31: 2024-W45 | E31: 21 | G31: 2024-W45 | H31: 20 | J31: 2024-W46 | K31: 12
D32: 2024-W46 | E32: 21 | G32: 2024-W46 | H32: 20 | J32: 2024-W47 | K32: 11
D33: 2024-W47 | E33: 21 | G33: 2024-W47 | H33: 20 | J33: 2024-W48 | K33: 13
D34: 2024-W48 | E34: 22 | G34: 2024-W48 | H34: 21 | J34: 2024-W49 | K34: 11
D35: 2024-W49 | E35: 28 | G35: 2024-W49 | H35: 27 | J35: 2024-W50 | K35: 16
D36: 2024-W50 | E36: 28 | G36: 2024-W50 | H36: 27 | J36: 2024-W51 | K36: 17
D37: 2024-W51 | E37: 28 | G37: 2024-W51 | H37: 28 | J37: 2024-W52 | K37: 17
D38: 2024-W52 | E38: 28 | G38: 2024-W52 | H38: 28 | J38: 2024-W53 | K38: 3
D39: 2024-W53 | E39: 5 | G39: 2024-W53 | H39: 5 | J39: Grand Total | K39: 180
D40: Grand Total | E40: 346 | G40: Grand Total | H40: 328
D42: Segmentation Analysis
H43: Segment A (Customer Type)
D44: Row Labels | E44: Order volume by customer type | G44: Row Labels | H44: Order volume by customer type | I44: Sum of Net revenue | K44: Delivered Orders (New customers) | L44: =COUNTIFS( urbanthreads_q4[Type], "New", urbanthreads_q4[Status], "Delivered" ) -> 253
D45: New | E45: 270 | G45: New | H45: 270 | I45: 786744 | K45: Returned Delivered Orders (New customers) | L45: =COUNTIFS( urbanthreads_q4[Type], "New", urbanthreads_q4[Status], "Delivered", urbanthreads_q4[Return?], "Yes" ) -> 147
D46: Returning | E46: 76 | G46: Returning | H46: 76 | I46: 233675
D47: Grand Total | E47: 346 | G47: Grand Total | H47: 346 | I47: 1020419 | K47: Delivered Orders (Returning customers) | L47: =COUNTIFS( urbanthreads_q4[Type], "Returning", urbanthreads_q4[Status], "Delivered" ) -> 75
K48: Returned Delivered Orders (Returning customers) | L48: =COUNTIFS( urbanthreads_q4[Type], "Returning", urbanthreads_q4[Status], "Delivered", urbanthreads_q4[Return?], "Yes" ) -> 33
D49: Return rate | E49: =E14/E13 -> 0.54878049 | G49: AOV for New customers | H49: =GETPIVOTDATA("Sum of Net revenue",$G$44,"Type","New")/GETPIVOTDATA("Order volume by customer type",$G$44,"Type","New") -> 2913.8667
D50: New customers (Return Rate) | E50: =L45/L44 -> 0.58102767 | G50: AOV for return customers | H50: =GETPIVOTDATA("Sum of Net revenue",$G$44,"Type","Returning")/GETPIVOTDATA("Order volume by customer type",$G$44,"Type","Returning") -> 3074.6711
D51: Returning customers (Return Rate) | E51: =L48/L47 -> 0.44 | G51: Overall AOV | H51: =GETPIVOTDATA("Sum of Net revenue",$G$44)/GETPIVOTDATA("Order volume by customer type",$G$44) -> 2949.1879 | J51: Status | K51: Delivered
G52: Status | H52: Delivered | J52: Return? | K52: Yes
H53: SegmentB(Order Source)
D54: Row Labels | E54: Order Volume by source | G54: Row Labels | H54: Order Volume by source(Delivered) | J54: Row Labels | K54: Order Volume by source(Returned)
D55: Instagram Shop | E55: 109 | G55: Instagram Shop | H55: 105 | J55: Instagram Shop | K55: 71
D56: Mobile App | E56: 116 | G56: Mobile App | H56: 108 | J56: Mobile App | K56: 61
D57: Website | E57: 121 | G57: Website | H57: 115 | J57: Website | K57: 48
D58: Grand Total | E58: 346 | G58: Grand Total | H58: 328 | J58: Grand Total | K58: 180
D60: Return rate (Instagram shop) | E60: =GETPIVOTDATA("Order ID",$J$54,"Source","Instagram Shop")/GETPIVOTDATA("Order ID",$G$54,"Source","Instagram Shop") -> 0.67619048
D61: Return rate (Mobile App) | E61: =GETPIVOTDATA("Order ID",$J$54,"Source","Mobile App")/GETPIVOTDATA("Order ID",$G$54,"Source","Mobile App") -> 0.56481481
D62: Return rate (Website) | E62: =GETPIVOTDATA("Order ID",$J$54,"Source","Website")/GETPIVOTDATA("Order ID",$G$54,"Source","Website") -> 0.4173913
H64: AOV by source
D65: Row Labels | E65: Sum of Net revenue | F65: Count of Order Date
D66: Instagram Shop | E66: 334586 | F66: 109
D67: Mobile App | E67: 328544 | F67: 116
D68: Website | E68: 357289 | F68: 121
D69: Grand Total | E69: 1020419 | F69: 346
D71: AOV (Instagram shop) | E71: =GETPIVOTDATA("Sum of Net revenue",$D$65,"Source","Instagram Shop")/GETPIVOTDATA("Count of Order Date",$D$65,"Source","Instagram Shop") -> 3069.5963
D72: AOV (Mobile App) | E72: =GETPIVOTDATA("Sum of Net revenue",$D$65,"Source","Mobile App")/GETPIVOTDATA("Count of Order Date",$D$65,"Source","Mobile App") -> 2832.2759
D73: AOV (Website) | E73: =GETPIVOTDATA("Sum of Net revenue",$D$65,"Source","Website")/GETPIVOTDATA("Count of Order Date",$D$65,"Source","Website") -> 2952.8017 | J73: Status | K73: Delivered
G74: Status | H74: Delivered | J74: Return? | K74: Yes
H75: SegmentC(Payment)
D76: Row Labels | E76: Payment type volume | G76: Row Labels | H76: Payment Type (Delivered) | J76: Row Labels | K76: Payment type volume
D77: COD | E77: 63 | G77: COD | H77: 46 | J77: COD | K77: 38
D78: Prepaid | E78: 283 | G78: Prepaid | H78: 282 | J78: Prepaid | K78: 142
D79: Grand Total | E79: 346 | G79: Grand Total | H79: 328 | J79: Grand Total | K79: 180
D81: Return rate(COD) | E81: =GETPIVOTDATA("Order ID",$J$76,"Payment Type","COD")/GETPIVOTDATA("Order ID",$G$76,"Payment Type","COD") -> 0.82608696
D82: Return rate(Prepaid) | E82: =GETPIVOTDATA("Order ID",$J$76,"Payment Type","Prepaid")/GETPIVOTDATA("Order ID",$G$76,"Payment Type","Prepaid") -> 0.5035461
H84: SegmentD(Product Category) | J84: Status | K84: Delivered
G85: Status | H85: Delivered | J85: Return? | K85: Yes
D87: Row Labels | E87: Category wise Order Volume | G87: Row Labels | H87: Category wise Order Volume(delivered) | J87: Row Labels | K87: Category wise Order Volume
D88: Accessories | E88: 68 | G88: Accessories | H88: 65 | J88: Accessories | K88: 16
D89: Bottoms | E89: 67 | G89: Bottoms | H89: 65 | J89: Bottoms | K89: 25
D90: Dresses | E90: 70 | G90: Dresses | H90: 66 | J90: Dresses | K90: 44
D91: Outerwear | E91: 68 | G91: Outerwear | H91: 65 | J91: Outerwear | K91: 52
D92: Tops | E92: 73 | G92: Tops | H92: 67 | J92: Tops | K92: 43
D93: Grand Total | E93: 346 | G93: Grand Total | H93: 328 | J93: Grand Total | K93: 180
D95: Return Rate(Accessories) | E95: =GETPIVOTDATA("Order ID",$J$87,"Category","Accessories")/GETPIVOTDATA("Order ID",$G$87,"Category","Accessories") -> 0.24615385
D96: Return Rate(Bottoms) | E96: =GETPIVOTDATA("Order ID",$J$87,"Category","Bottoms")/GETPIVOTDATA("Order ID",$G$87,"Category","Bottoms") -> 0.38461538
D97: Return Rate(Dresses) | E97: =GETPIVOTDATA("Order ID",$J$87,"Category","Dresses")/GETPIVOTDATA("Order ID",$G$87,"Category","Dresses") -> 0.66666667
D98: Return Rate(outerwear) | E98: =GETPIVOTDATA("Order ID",$J$87,"Category","Outerwear")/GETPIVOTDATA("Order ID",$G$87,"Category","Outerwear") -> 0.8 | O98: Status | P98: Delivered
D99: Return Rate(Tops) | E99: =GETPIVOTDATA("Order ID",$J$87,"Category","Tops")/GETPIVOTDATA("Order ID",$G$87,"Category","Tops") -> 0.64179104 | I99: Refund | J99: Processed | L99: Status | M99: Delivered | O99: Type | P99: New
I100: Ret Rec | J100: (Multiple Items) | L100: Type | M100: New | O100: Return? | P100: Yes
A101: KPI | B101: Definition | C101: Value | F101: Return to Origin Rate | I101: Refund Processing Rate | L101: First time buyer return rate(delivered orders new customers) | O101: First time buyer return rate(Returned orders new customers)
A102: GMV | B102: Σ order_total | C102: =SUM(urbanthreads_q4[Total]) -> 1023789 | F102: Row Labels | G102: Count of Order ID | I102: Count of Order ID | L102: Count of Order ID | O102: Count of Order ID
A103: Net Revenue | B103: GMV − Discounts | C103: =SUM(urbanthreads_q4[Net revenue]) -> 1020419 | F103: RTO | G103: 17 | I103: 173 | L103: 253 | O103: 147
A104: Return Rate | B104: Returned Delivered / Delivered | C104: =E14/E13 -> 0.54878049 | I104: Status | J104: Delivered
A105: RTO Rate | B105: RTO / Shipped Orders | C105: =GETPIVOTDATA("Order ID",$F$102,"Status","RTO")/E13 -> 0.051829268 | F105: Status | G105: Delivered | I105: Type | J105: Returning
A106: Refund Processing Rate | B106: Processed / Return Received | C106: =GETPIVOTDATA("Order ID",$I$102)/E14 -> 0.96111111 | F106: Type | G106: Returning | I106: Return? | J106: Yes
A107: First-Time Buyer Return Rate | B107: Returns(New) / Delivered(New) | C107: =GETPIVOTDATA("Order ID",$O$102)/GETPIVOTDATA("Order ID",$L$102) -> 0.58102767 | F107: Repeat time buyer return rate(delivered orders Returning Customers) | I107: Repeat time buyer return rate(Returned orders Returning Customers)
A108: Repeat Buyer Return Rate | B108: Returns(Returning) / Delivered(Returning) | C108: =GETPIVOTDATA("Order ID",$I$108)/GETPIVOTDATA("Order ID",$F$108) -> 0.44 | F108: Count of Order ID | I108: Count of Order ID
A109: Fulfillment Split | B109: Orders by Warehouse | C109: See below | F109: 75 | I109: 33
F112: Fullfilment split by warehouse
F113: Warehouse | G113: Orders Handled by warehouse | H113: Percentage
F114: Bangalore | G114: 93 | H114: =GETPIVOTDATA("Order ID",$F$113,"Warehouse","Bangalore")/GETPIVOTDATA("Order ID",$F$113) -> 0.26878613
...

Sheet Analysis
I1: Descriptive Analysis
I3: Summary(Final Values)
I4: Metric | J4: Value
I5: Total Orders | J5: =COUNTA(urbanthreads_q4[Order ID]) -> 346
I6: Total Revenue (After Discounts) | J6: =SUM(urbanthreads_q4[Net revenue]) -> 1020419
I7: Total Units Sold | J7: =SUM(urbanthreads_q4[Qty]) -> 409
I8: Average Order Value (AOV) | J8: =SUM(urbanthreads_q4[Net revenue]) / COUNTA(urbanthreads_q4[Order ID]) -> 2949.1879
I9: Overall Return Rate | J9: =Working_Analysis!E14/Working_Analysis!E13 -> 0.54878049
I11: Monthly Order Breakdown(Final Values)
I12: Month | J12: Orders
I13: 45566 | J13: =COUNTIFS(urbanthreads_q4[Order Date],">=01-10-2024",urbanthreads_q4[Order Date],"<=31-10-2024") -> 131
I14: 45597 | J14: =COUNTIFS( urbanthreads_q4[Order Date],">=01-11-2024", urbanthreads_q4[Order Date],"<=30-11-2024" ) -> 93
I15: 45627 | J15: =COUNTIFS(urbanthreads_q4[Order Date],">=01-12-2024",urbanthreads_q4[Order Date],"<=31-12-2024") -> 121
I16: Total(Valid Orders) | J16: =SUM(J13:J15) -> 345
I18: TREND IDENTIFICATION(Weekly)
F19: {=Working_Analysis!D24:E40} -> Week Number | G19: Total Orders (By week) | I19: {=Working_Analysis!G24:H40} -> Week Number | J19: Total Orders Delivered | L19: {=Working_Analysis!J24:K39} -> Week Number | M19: Returned Delivered Orders
F20: 2024-W2 | G20: 1 | I20: 2024-W2 | J20: 1 | L20: 2024-W40 | M20: 11
F21: 2024-W40 | G21: 26 | I21: 2024-W40 | J21: 23 | L21: 2024-W41 | M21: 11
F22: 2024-W41 | G22: 29 | I22: 2024-W41 | J22: 27 | L22: 2024-W42 | M22: 13
F23: 2024-W42 | G23: 28 | I23: 2024-W42 | J23: 26 | L23: 2024-W43 | M23: 10
F24: 2024-W43 | G24: 27 | I24: 2024-W43 | J24: 24 | L24: 2024-W44 | M24: 24
F25: 2024-W44 | G25: 33 | H25: (Diwali Spike Week) | I25: 2024-W44 | J25: 31 | L25: 2024-W45 | M25: 11
F26: 2024-W45 | G26: 21 | I26: 2024-W45 | J26: 20 | L26: 2024-W46 | M26: 12
F27: 2024-W46 | G27: 21 | I27: 2024-W46 | J27: 20 | L27: 2024-W47 | M27: 11
F28: 2024-W47 | G28: 21 | I28: 2024-W47 | J28: 20 | L28: 2024-W48 | M28: 13
F29: 2024-W48 | G29: 22 | I29: 2024-W48 | J29: 21 | L29: 2024-W49 | M29: 11
F30: 2024-W49 | G30: 28 | I30: 2024-W49 | J30: 27 | L30: 2024-W50 | M30: 16
F31: 2024-W50 | G31: 28 | I31: 2024-W50 | J31: 27 | L31: 2024-W51 | M31: 17
F32: 2024-W51 | G32: 28 | I32: 2024-W51 | J32: 28 | L32: 2024-W52 | M32: 17
F33: 2024-W52 | G33: 28 | I33: 2024-W52 | J33: 28 | L33: 2024-W53 | M33: 3
F34: 2024-W53 | G34: 5 | I34: 2024-W53 | J34: 5 | L34: Grand Total | M34: 180
F35: Grand Total | G35: 346 | I35: Grand Total | J35: 328
I37: Segmentation Analysis
F38: Segment A — Customer Type
F39: Customer Type | G39: Orders | H39: AOV | I39: Return Rate
F40: New | G40: =COUNTIFS(urbanthreads_q4[Type],"New") -> 270 | H40: =SUMIFS(urbanthreads_q4[Net revenue],urbanthreads_q4[Type],"New") / COUNTIFS(urbanthreads_q4[Type],"New") -> 2913.8667 | I40: =Working_Analysis!E50 -> 0.58102767
F41: Returning | G41: =COUNTIFS(urbanthreads_q4[Type],"Returning") -> 76 | H41: =SUMIFS(urbanthreads_q4[Net revenue],urbanthreads_q4[Type],"Returning") / COUNTIFS(urbanthreads_q4[Type],"Returning") -> 3074.6711 | I41: =Working_Analysis!E51 -> 0.44
F43: Segment B — Order Source
F44: Source | G44: Orders | H44: AOV | I44: Return Rate
F45: Instagram Shop | G45: =COUNTIFS(urbanthreads_q4[Source],"Instagram Shop") -> 109 | H45: =SUMIFS(urbanthreads_q4[Net revenue],urbanthreads_q4[Source],"Instagram Shop") / COUNTIFS(urbanthreads_q4[Source],"Instagram Shop") -> 3069.5963 | I45: =Working_Analysis!E60 -> 0.67619048
F46: Mobile App | G46: =COUNTIFS(urbanthreads_q4[Source],"Mobile App") -> 116 | H46: =SUMIFS(urbanthreads_q4[Net revenue],urbanthreads_q4[Source],"Mobile App") / COUNTIFS(urbanthreads_q4[Source],"Mobile App") -> 2832.2759 | I46: =Working_Analysis!E61 -> 0.56481481
F47: Website | G47: =COUNTIFS(urbanthreads_q4[Source],"Website") -> 121 | H47: =SUMIFS(urbanthreads_q4[Net revenue],urbanthreads_q4[Source],"Website") / COUNTIFS(urbanthreads_q4[Source],"Website") -> 2952.8017 | I47: =Working_Analysis!E62 -> 0.4173913
F49: Segment C — Payment Method
F50: Payment Type | G50: Orders | H50: Return Rate
F51: COD | G51: =GETPIVOTDATA("Order ID",Working_Analysis!$D$76,"Payment Type","COD") -> 63 | H51: =Working_Analysis!E81 -> 0.82608696
F52: Prepaid | G52: =GETPIVOTDATA("Order ID",Working_Analysis!$D$76,"Payment Type","Prepaid") -> 283 | H52: =Working_Analysis!E82 -> 0.5035461
F54: Segment D — Product Category
F55: Category | G55: Orders | H55: Return Rate
F56: Accessories | G56: =GETPIVOTDATA("Order ID",Working_Analysis!$D$87,"Category","Accessories") -> 68 | H56: =Working_Analysis!E95 -> 0.24615385
F57: Bottoms | G57: =GETPIVOTDATA("Order ID",Working_Analysis!$D$87,"Category","Bottoms") -> 67 | H57: =Working_Analysis!E96 -> 0.38461538
F58: Dresses | G58: =GETPIVOTDATA("Order ID",Working_Analysis!$D$87,"Category","Dresses") -> 70 | H58: =Working_Analysis!E97 -> 0.66666667
F59: Outerwear | G59: =GETPIVOTDATA("Order ID",Working_Analysis!$D$87,"Category","Outerwear") -> 68 | H59: =Working_Analysis!E98 -> 0.8
F60: Tops | G60: =GETPIVOTDATA("Order ID",Working_Analysis!$D$87,"Category","Tops") -> 73 | H60: =Working_Analysis!E99 -> 0.64179104
I62: KPI Calculations
F63: KPI | G63: Final value | J63: Fulfillment Split (FINAL VALUES)
F64: GMV | G64: =SUM(urbanthreads_q4[Total]) -> 1023789 | I64: {=Working_Analysis!F113:H117} -> Warehouse | J64: Orders Handled by warehouse | K64: Percentage
F65: Net Revenue | G65: =SUM(urbanthreads_q4[Net revenue]) -> 1020419 | I65: Bangalore | J65: 93 | K65: 0.26878613
F66: Overall Return Rate | G66: =Working_Analysis!E15 -> 0.54878049 | I66: Delhi | J66: 132 | K66: 0.38150289
F67: RTO Rate | G67: =GETPIVOTDATA("Order ID",Working_Analysis!$F$102,"Status","RTO")/Working_Analysis!E13 -> 0.051829268 | I67: Mumbai | J67: 121 | K67: 0.34971098
F68: Refund Processing Rate | G68: =Working_Analysis!C106 -> 0.96111111 | I68: Grand Total | J68: 346 | K68: 1
F69: First Time Buyer Return Rate | G69: =Working_Analysis!C107 -> 0.58102767
F70: Repeat Buyer Return Rate | G70: =Working_Analysis!C108 -> 0.44
I72: Business Interpretation
I91: PROBLEM-SOLVING

Sheet Visualization
D1: Urban Threads Q4 2024 — Returns & Fulfillment Performance Dashboard

Sheet Recommendations
I1: Recommendations
